Workbook

Sheet Global
A1: Proveedor | B1: Codigo_ML | C1: SKU | D1: Titulo | E1: Status | F1: Stock_FULL | G1: Stock_FLEX | H1: Stock_Total | I1: Supermarket | J1: Costo | K1: Valorización | L1: V30D | M1: V30FULL | N1: V30FLEX | O1: V30CENTRO | P1: RepFULL | Q1: RepFLEX | R1: RepTotal | S1: Permalink
A2: {=XLOOKUP(B2,Costos_Proveedores!$B$2:$B$2000,Costos_Proveedores!$A$2:$A$2000)} -> MULI | B2: MLC2853724594 | D2: Espejo Para Maquillaje Espejo Doble De Mesa Con Aumento 36cm | E2: closed | F2: 1 | G2: 1 | H2: =IF(I2="Sí",F2,F2+G2) -> 2 | I2: No | J2: =VLOOKUP(B2,Costos_Proveedores!$B$2:$J$1000,9,FALSE()) -> 4550 | K2: =IFERROR(H2*J2,0) -> 9100 | P2: =IF(M2>=F2,M2-F2,0) -> 0 | Q2: =IF(N2+O2-G2>=0,N2+O2-G2,0) -> 0 | R2: =P2+Q2 -> 0 | S2: https://articulo.mercadolibre.cl/MLC-2853724594-espejo-para-maquillaje-espejo-doble-de-mesa-con-aumento-36cm-_JM
A3: {=XLOOKUP(B3,Costos_Proveedores!$B$2:$B$2000,Costos_Proveedores!$A$2:$A$2000)} -> MULI | B3: MLC1604270301 | C3: ML272 | D3: Organizador Y Separador De Cubiertos | E3: closed | F3: 0 | G3: 0 | H3: =IF(I3="Sí",F3,F3+G3) -> 0 | I3: No | J3: =VLOOKUP(B3,Costos_Proveedores!$B$2:$J$1000,9,FALSE()) -> 1848 | K3: =IFERROR(H3*J3,0) -> 0 | L3: =SUM(M3:O3) -> 39 | M3: 39 | N3: 0 | O3: 0 | P3: =IF(M3>=F3,M3-F3,0) -> 39 | Q3: =IF(N3+O3-G3>=0,N3+O3-G3,0) -> 0 | R3: =P3+Q3 -> 39 | S3: https://articulo.mercadolibre.cl/MLC-1604270301-organizador-y-separador-de-cubiertos-_JM
A4: {=XLOOKUP(B4,Costos_Proveedores!$B$2:$B$2000,Costos_Proveedores!$A$2:$A$2000)} -> MULI | B4: MLC1582676309 | C4: ML247 | D4: Tabla Planchar Tabla De Planchar Metal Y Tela 110 Cm Mangas Al Azar Multicolor | E4: paused | G4: 0 | H4: =IF(I4="Sí",F4,F4+G4) -> 0 | I4: No | J4: =VLOOKUP(B4,Costos_Proveedores!$B$2:$J$1000,9,FALSE()) -> 14400 | K4: =IFERROR(H4*J4,0) -> 0 | P4: =IF(M4>=F4,M4-F4,0) -> 0 | Q4: =IF(N4+O4-G4>=0,N4+O4-G4,0) -> 0 | R4: =P4+Q4 -> 0 | S4: https://articulo.mercadolibre.cl/MLC-1582676309-tabla-planchar-tabla-de-planchar-metal-y-tela-110-cm-mangas-al-azar-multicolor-_JM
A5: {=XLOOKUP(B5,Costos_Proveedores!$B$2:$B$2000,Costos_Proveedores!$A$2:$A$2000)} -> MULI | B5: MLC1582663459 | C5: ML256 | D5: Organizador Verdulero Frutero 3 Niveles Metálico Inoxidable Plateado | E5: paused | G5: 0 | H5: =IF(I5="Sí",F5,F5+G5) -> 0 | I5: No | J5: =VLOOKUP(B5,Costos_Proveedores!$B$2:$J$1000,9,FALSE()) -> 10080 | K5: =IFERROR(H5*J5,0) -> 0 | P5: =IF(M5>=F5,M5-F5,0) -> 0 | Q5: =IF(N5+O5-G5>=0,N5+O5-G5,0) -> 0 | R5: =P5+Q5 -> 0 | S5: https://articulo.mercadolibre.cl/MLC-1582663459-organizador-verdulero-frutero-3-niveles-metalico-inoxidable-plateado-_JM
A6: {=XLOOKUP(B6,Costos_Proveedores!$B$2:$B$2000,Costos_Proveedores!$A$2:$A$2000)} -> MULI | B6: MLC1582589593 | C6: WF33322 | D6: Fuente Pileta Cascada De Agua Jesus Grande 39 Cm Con Luz Gris | E6: paused | G6: 0 | H6: =IF(I6="Sí",F6,F6+G6) -> 0 | I6: No | J6: =VLOOKUP(B6,Costos_Proveedores!$B$2:$J$1000,9,FALSE()) -> 16800 | K6: =IFERROR(H6*J6,0) -> 0 | P6: =IF(M6>=F6,M6-F6,0) -> 0 | Q6: =IF(N6+O6-G6>=0,N6+O6-G6,0) -> 0 | R6: =P6+Q6 -> 0 | S6: https://articulo.mercadolibre.cl/MLC-1582589593-fuente-pileta-cascada-de-agua-jesus-grande-39-cm-con-luz-gris-_JM
A7: {=XLOOKUP(B7,Costos_Proveedores!$B$2:$B$2000,Costos_Proveedores!$A$2:$A$2000)} -> MULI | B7: MLC1582563757 | C7: WF33313 | D7: Fuente Pileta Cascada De Agua Querubín Con Luz Grande 28cm Gris | E7: paused | G7: 0 | H7: =IF(I7="Sí",F7,F7+G7) -> 0 | I7: No | J7: =VLOOKUP(B7,Costos_Proveedores!$B$2:$J$1000,9,FALSE()) -> 12800 | K7: =IFERROR(H7*J7,0) -> 0 | P7: =IF(M7>=F7,M7-F7,0) -> 0 | Q7: =IF(N7+O7-G7>=0,N7+O7-G7,0) -> 0 | R7: =P7+Q7 -> 0 | S7: https://articulo.mercadolibre.cl/MLC-1582563757-fuente-pileta-cascada-de-agua-querubin-con-luz-grande-28cm-gris-_JM
A8: {=XLOOKUP(B8,Costos_Proveedores!$B$2:$B$2000,Costos_Proveedores!$A$2:$A$2000)} -> MULI | B8: MLC1582563657 | C8: 104922 | D8: Pack 4 Vasos Con Bombilla Y Tapa 600 Ml Vidrio Shopero 600ml Multicolor | E8: active | G8: 2 | H8: =IF(I8="Sí",F8,F8+G8) -> 2 | I8: No | J8: =VLOOKUP(B8,Costos_Proveedores!$B$2:$J$1000,9,FALSE()) -> 4032 | K8: =IFERROR(H8*J8,0) -> 8064 | L8: 5 | M8: 0 | N8: 0 | O8: 5 | P8: =IF(M8>=F8,M8-F8,0) -> 0 | Q8: =IF(N8+O8-G8>=0,N8+O8-G8,0) -> 3 | R8: =P8+Q8 -> 3 | S8: https://articulo.mercadolibre.cl/MLC-1582563657-pack-4-vasos-con-bombilla-y-tapa-600-ml-vidrio-shopero-600ml-multicolor-_JM
A9: {=XLOOKUP(B9,Costos_Proveedores!$B$2:$B$2000,Costos_Proveedores!$A$2:$A$2000)} -> MULI | B9: MLC1582511883 | C9: 45100 | D9: Pack 6 Platos Hondos Floreado Opal Templado 22cm Blanco | E9: paused | G9: 0 | H9: =IF(I9="Sí",F9,F9+G9) -> 0 | I9: No | J9: =VLOOKUP(B9,Costos_Proveedores!$B$2:$J$1000,9,FALSE()) -> 6852 | K9: =IFERROR(H9*J9,0) -> 0 | P9: =IF(M9>=F9,M9-F9,0) -> 0 | Q9: =IF(N9+O9-G9>=0,N9+O9-G9,0) -> 0 | R9: =P9+Q9 -> 0 | S9: https://articulo.mercadolibre.cl/MLC-1582511883-pack-6-platos-hondos-floreado-opal-templado-22cm-blanco-_JM
A10: {=XLOOKUP(B10,Costos_Proveedores!$B$2:$B$2000,Costos_Proveedores!$A$2:$A$2000)} -> MULI | B10: MLC3092101060 | C10: 108484 | D10: Pack 6 Piso Deportivo Modular Goma Eva 60x60x1 Cm Fitness Blanco Blanco Industrial | E10: paused | F10: 0 | G10: 0 | H10: =IF(I10="Sí",F10,F10+G10) -> 0 | I10: No | J10: =VLOOKUP(B10,Costos_Proveedores!$B$2:$J$1000,9,FALSE()) -> 8400 | K10: =IFERROR(H10*J10,0) -> 0 | P10: =IF(M10>=F10,M10-F10,0) -> 0 | Q10: =IF(N10+O10-G10>=0,N10+O10-G10,0) -> 0 | R10: =P10+Q10 -> 0 | S10: https://articulo.mercadolibre.cl/MLC-3092101060-pack-6-piso-deportivo-modular-goma-eva-60x60x1-cm-fitness-blanco-blanco-industrial-_JM
A11: {=XLOOKUP(B11,Costos_Proveedores!$B$2:$B$2000,Costos_Proveedores!$A$2:$A$2000)} -> MULI | B11: MLC3092101058 | C11: 108483 | D11: Pack 6 Piso Deportivo Modular Goma Eva 60x60x1 Cm Fitness Negro Negro Industrial | E11: paused | F11: 0 | G11: 0 | H11: =IF(I11="Sí",F11,F11+G11) -> 0 | I11: No | J11: =VLOOKUP(B11,Costos_Proveedores!$B$2:$J$1000,9,FALSE()) -> 8400 | K11: =IFERROR(H11*J11,0) -> 0 | L11: 31 | M11: 31 | N11: 0 | O11: 0 | P11: =IF(M11>=F11,M11-F11,0) -> 31 | Q11: =IF(N11+O11-G11>=0,N11+O11-G11,0) -> 0 | R11: =P11+Q11 -> 31 | S11: https://articulo.mercadolibre.cl/MLC-3092101058-pack-6-piso-deportivo-modular-goma-eva-60x60x1-cm-fitness-negro-negro-industrial-_JM
A12: {=XLOOKUP(B12,Costos_Proveedores!$B$2:$B$2000,Costos_Proveedores!$A$2:$A$2000)} -> MULI | B12: MLC2933761314 | C12: 106551G | D12: Basurero Metálico Con Pedal 8 Litros Pedal Acabado Madera Gris | E12: paused | F12: 0 | G12: 0 | H12: =IF(I12="Sí",F12,F12+G12) -> 0 | I12: No | J12: =VLOOKUP(B12,Costos_Proveedores!$B$2:$J$1000,9,FALSE()) -> 8400 | K12: =IFERROR(H12*J12,0) -> 0 | P12: =IF(M12>=F12,M12-F12,0) -> 0 | Q12: =IF(N12+O12-G12>=0,N12+O12-G12,0) -> 0 | R12: =P12+Q12 -> 0 | S12: https://articulo.mercadolibre.cl/MLC-2933761314-basurero-metalico-con-pedal-8-litros-pedal-acabado-madera-gris-_JM
A13: {=XLOOKUP(B13,Costos_Proveedores!$B$2:$B$2000,Costos_Proveedores!$A$2:$A$2000)} -> MULI | B13: MLC2933761312 | C13: 106551C | D13: Basurero Metálico Con Pedal 8 Litros Pedal Acabado Madera Marrón | E13: paused | F13: 0 | G13: 0 | H13: =IF(I13="Sí",F13,F13+G13) -> 0 | I13: No | J13: =VLOOKUP(B13,Costos_Proveedores!$B$2:$J$1000,9,FALSE()) -> 8400 | K13: =IFERROR(H13*J13,0) -> 0 | L13: 7 | M13: 7 | N13: 0 | O13: 0 | P13: =IF(M13>=F13,M13-F13,0) -> 7 | Q13: =IF(N13+O13-G13>=0,N13+O13-G13,0) -> 0 | R13: =P13+Q13 -> 7 | S13: https://articulo.mercadolibre.cl/MLC-2933761312-basurero-metalico-con-pedal-8-litros-pedal-acabado-madera-marron-_JM
A14: {=XLOOKUP(B14,Costos_Proveedores!$B$2:$B$2000,Costos_Proveedores!$A$2:$A$2000)} -> MULI | B14: MLC2863704914 | C14: 107180 | D14: Pack 4 Goma Eva Piso Alfombra Antigolpes 60x60x1cm Madera Marrón Piso Flotante | E14: paused | F14: 0 | G14: 15 | H14: =IF(I14="Sí",F14,F14+G14) -> 15 | I14: No | J14: =VLOOKUP(B14,Costos_Proveedores!$B$2:$J$1000,9,FALSE()) -> 5880 | K14: =IFERROR(H14*J14,0) -> 88200 | P14: =IF(M14>=F14,M14-F14,0) -> 0 | Q14: =IF(N14+O14-G14>=0,N14+O14-G14,0) -> 0 | R14: =P14+Q14 -> 0 | S14: https://articulo.mercadolibre.cl/MLC-2863704914-pack-4-goma-eva-piso-alfombra-antigolpes-60x60x1cm-madera-marron-piso-flotante-_JM
A15: {=XLOOKUP(B15,Costos_Proveedores!$B$2:$B$2000,Costos_Proveedores!$A$2:$A$2000)} -> MULI | B15: MLC2863704912 | C15: 107179 | D15: Pack 4 Goma Eva Piso Alfombra Antigolpes 60x60x1cm Madera Beige Lisa | E15: paused | F15: 0 | G15: 0 | H15: =IF(I15="Sí",F15,F15+G15) -> 0 | I15: No | J15: =VLOOKUP(B15,Costos_Proveedores!$B$2:$J$1000,9,FALSE()) -> 6720 | K15: =IFERROR(H15*J15,0) -> 0 | P15: =IF(M15>=F15,M15-F15,0) -> 0 | Q15: =IF(N15+O15-G15>=0,N15+O15-G15,0) -> 0 | R15: =P15+Q15 -> 0 | S15: https://articulo.mercadolibre.cl/MLC-2863704912-pack-4-goma-eva-piso-alfombra-antigolpes-60x60x1cm-madera-beige-lisa-_JM
A16: {=XLOOKUP(B16,Costos_Proveedores!$B$2:$B$2000,Costos_Proveedores!$A$2:$A$2000)} -> MULI | B16: MLC2853425396 | C16: 107833 | D16: Basurero Metálico Con Pedal 12 Litros Plateado Acero Canasta Gris | E16: paused | F16: 0 | G16: 12 | H16: =IF(I16="Sí",F16,F16+G16) -> 12 | I16: No | J16: =VLOOKUP(B16,Costos_Proveedores!$B$2:$J$1000,9,FALSE()) -> 8400 | K16: =IFERROR(H16*J16,0) -> 100800 | L16: 56 | M16: 56 | N16: 0 | O16: 0 | P16: =IF(M16>=F16,M16-F16,0) -> 56 | Q16: =IF(N16+O16-G16>=0,N16+O16-G16,0) -> 0 | R16: =P16+Q16 -> 56 | S16: https://articulo.mercadolibre.cl/MLC-2853425396-basurero-metalico-con-pedal-12-litros-plateado-acero-canasta-gris-_JM
A17: {=XLOOKUP(B17,Costos_Proveedores!$B$2:$B$2000,Costos_Proveedores!$A$2:$A$2000)} -> MULI | B17: MLC2853290088 | C17: 788133 | D17: Pack 24 Burbujas Juguete Sorpresa Cumpleaños Regalo Paseo Multicolor | E17: paused | F17: 0 | G17: 0 | H17: =IF(I17="Sí",F17,F17+G17) -> 0 | I17: No | J17: =VLOOKUP(B17,Costos_Proveedores!$B$2:$J$1000,9,FALSE()) -> 4200 | K17: =IFERROR(H17*J17,0) -> 0 | P17: =IF(M17>=F17,M17-F17,0) -> 0 | Q17: =IF(N17+O17-G17>=0,N17+O17-G17,0) -> 0 | R17: =P17+Q17 -> 0 | S17: https://articulo.mercadolibre.cl/MLC-2853290088-pack-24-burbujas-juguete-sorpresa-cumpleanos-regalo-paseo-multicolor-_JM
A18: {=XLOOKUP(B18,Costos_Proveedores!$B$2:$B$2000,Costos_Proveedores!$A$2:$A$2000)} -> MULI | B18: MLC2853171858 | D18: Set 10 30x30 Alfombra Infantil Goma Eva Cuadros Bebes Niños | E18: paused | H18: =IF(I18="Sí",F18,F18+G18) -> 0 | I18: No | J18: =VLOOKUP(B18,Costos_Proveedores!$B$2:$J$1000,9,FALSE()) -> 2730 | K18: =IFERROR(H18*J18,0) -> 0 | P18: =IF(M18>=F18,M18-F18,0) -> 0 | Q18: =IF(N18+O18-G18>=0,N18+O18-G18,0) -> 0 | R18: =P18+Q18 -> 0 | S18: https://articulo.mercadolibre.cl/MLC-2853171858-set-10-30x30-alfombra-infantil-goma-eva-cuadros-bebes-ninos-_JM
A19: {=XLOOKUP(B19,Costos_Proveedores!$B$2:$B$2000,Costos_Proveedores!$A$2:$A$2000)} -> MULI | B19: MLC1583375395 | C19: 103366 | D19: Basurero Metálico Con Pedal 3 Litros Plateado Acero Canasta Gris | E19: paused | F19: 0 | G19: 0 | H19: =IF(I19="Sí",F19,F19+G19) -> 0 | I19: No | J19: =VLOOKUP(B19,Costos_Proveedores!$B$2:$J$1000,9,FALSE()) -> 3780 | K19: =IFERROR(H19*J19,0) -> 0 | P19: =IF(M19>=F19,M19-F19,0) -> 0 | Q19: =IF(N19+O19-G19>=0,N19+O19-G19,0) -> 0 | R19: =P19+Q19 -> 0 | S19: https://articulo.mercadolibre.cl/MLC-1583375395-basurero-metalico-con-pedal-3-litros-plateado-acero-canasta-gris-_JM
A20: {=XLOOKUP(B20,Costos_Proveedores!$B$2:$B$2000,Costos_Proveedores!$A$2:$A$2000)} -> MULI | B20: MLC1583337113 | C20: 103368 | D20: Basurero Metálico Con Pedal 8 Litros Plateado Acero Canasta | E20: paused | F20: 0 | G20: 0 | H20: =IF(I20="Sí",F20,F20+G20) -> 0 | I20: No | J20: =VLOOKUP(B20,Costos_Proveedores!$B$2:$J$1000,9,FALSE()) -> 6720 | K20: =IFERROR(H20*J20,0) -> 0 | P20: =IF(M20>=F20,M20-F20,0) -> 0 | Q20: =IF(N20+O20-G20>=0,N20+O20-G20,0) -> 0 | R20: =P20+Q20 -> 0 | S20: https://articulo.mercadolibre.cl/MLC-1583337113-basurero-metalico-con-pedal-8-litros-plateado-acero-canasta-_JM
A21: {=XLOOKUP(B21,Costos_Proveedores!$B$2:$B$2000,Costos_Proveedores!$A$2:$A$2000)} -> MULI | B21: MLC1583327473 | C21: 103370 | D21: Basurero Metálico Con Pedal 20 Litros Plateado Acero Canasta Acero Inox Brillante | E21: active | F21: 25 | G21: 0 | H21: =IF(I21="Sí",F21,F21+G21) -> 25 | I21: No | J21: =VLOOKUP(B21,Costos_Proveedores!$B$2:$J$1000,9,FALSE()) -> 11760 | K21: =IFERROR(H21*J21,0) -> 294000 | L21: 30 | M21: 31 | N21: 0 | O21: 0 | P21: =IF(M21>=F21,M21-F21,0) -> 6 | Q21: =IF(N21+O21-G21>=0,N21+O21-G21,0) -> 0 | R21: =P21+Q21 -> 6 | S21: https://articulo.mercadolibre.cl/MLC-1583327473-basurero-metalico-con-pedal-20-litros-plateado-acero-canasta-acero-inox-brillante-_JM
A22: {=XLOOKUP(B22,Costos_Proveedores!$B$2:$B$2000,Costos_Proveedores!$A$2:$A$2000)} -> MULI | B22: MLC3086615012 | C22: 107583B | D22: Espejo Para Maquillaje Espejo Doble De Mesa Con Aumento 36cm Blanco | E22: active | F22: 2 | G22: 0 | H22: =IF(I22="Sí",F22,F22+G22) -> 2 | I22: No | J22: =VLOOKUP(B22,Costos_Proveedores!$B$2:$J$1000,9,FALSE()) -> 4550 | K22: =IFERROR(H22*J22,0) -> 9100 | L22: 2 | M22: 2 | N22: 0 | O22: 0 | P22: =IF(M22>=F22,M22-F22,0) -> 0 | Q22: =IF(N22+O22-G22>=0,N22+O22-G22,0) -> 0 | R22: =P22+Q22 -> 0 | S22: https://articulo.mercadolibre.cl/MLC-3086615012-espejo-para-maquillaje-espejo-doble-de-mesa-con-aumento-36cm-blanco-_JM
A23: {=XLOOKUP(B23,Costos_Proveedores!$B$2:$B$2000,Costos_Proveedores!$A$2:$A$2000)} -> MULI | B23: MLC3086615010 | C23: 107583R | D23: Espejo Para Maquillaje Espejo Doble De Mesa Con Aumento 36cm Rosado | E23: paused | F23: 0 | G23: 6 | H23: =IF(I23="Sí",F23,F23+G23) -> 6 | I23: No | J23: =VLOOKUP(B23,Costos_Proveedores!$B$2:$J$1000,9,FALSE()) -> 4550 | K23: =IFERROR(H23*J23,0) -> 27300 | L23: 1 | M23: 1 | N23: 0 | O23: 0 | P23: =IF(M23>=F23,M23-F23,0) -> 1 | Q23: =IF(N23+O23-G23>=0,N23+O23-G23,0) -> 0 | R23: =P23+Q23 -> 1 | S23: https://articulo.mercadolibre.cl/MLC-3086615010-espejo-para-maquillaje-espejo-doble-de-mesa-con-aumento-36cm-rosado-_JM
A24: {=XLOOKUP(B24,Costos_Proveedores!$B$2:$B$2000,Costos_Proveedores!$A$2:$A$2000)} -> MULI | B24: MLC2853699866 | C24: NE6511 | D24: Reloj De Cocina Análogo Grande Dorado Reloj De Pared 60cm Dorado Blanco | E24: paused | F24: 0 | G24: 0 | H24: =IF(I24="Sí",F24,F24+G24) -> 0 | I24: No | J24: =VLOOKUP(B24,Costos_Proveedores!$B$2:$J$1000,9,FALSE()) -> 6720 | K24: =IFERROR(H24*J24,0) -> 0 | P24: =IF(M24>=F24,M24-F24,0) -> 0 | Q24: =IF(N24+O24-G24>=0,N24+O24-G24,0) -> 0 | R24: =P24+Q24 -> 0 | S24: https://articulo.mercadolibre.cl/MLC-2853699866-reloj-de-cocina-analogo-grande-dorado-reloj-de-pared-60cm-dorado-blanco-_JM
A25: {=XLOOKUP(B25,Costos_Proveedores!$B$2:$B$2000,Costos_Proveedores!$A$2:$A$2000)} -> MULI | B25: MLC1583743561 | C25: WF33356 | D25: Pileta Y Cascada De Agua Buda Meditación Feng Shui Con Luz Gris | E25: paused | G25: 0 | H25: =IF(I25="Sí",F25,F25+G25) -> 0 | I25: No | J25: =VLOOKUP(B25,Costos_Proveedores!$B$2:$J$1000,9,FALSE()) -> 12600 | K25: =IFERROR(H25*J25,0) -> 0 | P25: =IF(M25>=F25,M25-F25,0) -> 0 | Q25: =IF(N25+O25-G25>=0,N25+O25-G25,0) -> 0 | R25: =P25+Q25 -> 0 | S25: https://articulo.mercadolibre.cl/MLC-1583743561-pileta-y-cascada-de-agua-buda-meditacion-feng-shui-con-luz-gris-_JM
A26: {=XLOOKUP(B26,Costos_Proveedores!$B$2:$B$2000,Costos_Proveedores!$A$2:$A$2000)} -> MULI | B26: MLC2855683304 | C26: LB404002 | D26: Set 4 Libros Para Colorear Antiestrés 64 Paginas Extraibles | E26: active | F26: 5 | G26: 12 | H26: =IF(I26="Sí",F26,F26+G26) -> 17 | I26: No | J26: =VLOOKUP(B26,Costos_Proveedores!$B$2:$J$1000,9,FALSE()) -> 6720 | K26: =IFERROR(H26*J26,0) -> 114240 | L26: 6 | M26: 4 | N26: 2 | O26: 0 | P26: =IF(M26>=F26,M26-F26,0) -> 0 | Q26: =IF(N26+O26-G26>=0,N26+O26-G26,0) -> 0 | R26: =P26+Q26 -> 0 | S26: https://articulo.mercadolibre.cl/MLC-2855683304-set-4-libros-para-colorear-antiestres-64-paginas-extraibles-_JM
A27: {=XLOOKUP(B27,Costos_Proveedores!$B$2:$B$2000,Costos_Proveedores!$A$2:$A$2000)} -> MULI | B27: MLC2855681612 | C27: 105738 | D27: Set Jarra Y 6 Vasos Conjunto Jarra 2 Litros Y 6 Vasos Vidrio Transparente | E27: paused | G27: 0 | H27: =IF(I27="Sí",F27,F27+G27) -> 0 | I27: No | J27: =VLOOKUP(B27,Costos_Proveedores!$B$2:$J$1000,9,FALSE()) -> 7560 | K27: =IFERROR(H27*J27,0) -> 0 | P27: =IF(M27>=F27,M27-F27,0) -> 0 | Q27: =IF(N27+O27-G27>=0,N27+O27-G27,0) -> 0 | R27: =P27+Q27 -> 0 | S27: https://articulo.mercadolibre.cl/MLC-2855681612-set-jarra-y-6-vasos-conjunto-jarra-2-litros-y-6-vasos-vidrio-transparente-_JM
A28: {=XLOOKUP(B28,Costos_Proveedores!$B$2:$B$2000,Costos_Proveedores!$A$2:$A$2000)} -> MULI | B28: MLC2855651866 | C28: 107427 | D28: 28cm Portacupcake Porta Torta Porta Cupcakes Campana Vidrio Transparente | E28: paused | F28: 0 | G28: 0 | H28: =IF(I28="Sí",F28,F28+G28) -> 0 | I28: No | J28: =VLOOKUP(B28,Costos_Proveedores!$B$2:$J$1000,9,FALSE()) -> 5880 | K28: =IFERROR(H28*J28,0) -> 0 | P28: =IF(M28>=F28,M28-F28,0) -> 0 | Q28: =IF(N28+O28-G28>=0,N28+O28-G28,0) -> 0 | R28: =P28+Q28 -> 0 | S28: https://articulo.mercadolibre.cl/MLC-2855651866-28cm-portacupcake-porta-torta-porta-cupcakes-campana-vidrio-transparente-_JM
A29: {=XLOOKUP(B29,Costos_Proveedores!$B$2:$B$2000,Costos_Proveedores!$A$2:$A$2000)} -> MULI | B29: MLC2855615494 | C29: WF33333 | D29: Fuente De Agua Pileta De Agua Buda Feng Shui 18 Cm Con Luz Gris | E29: paused | F29: 0 | G29: 0 | H29: =IF(I29="Sí",F29,F29+G29) -> 0 | I29: No | J29: =VLOOKUP(B29,Costos_Proveedores!$B$2:$J$1000,9,FALSE()) -> 5880 | K29: =IFERROR(H29*J29,0) -> 0 | P29: =IF(M29>=F29,M29-F29,0) -> 0 | Q29: =IF(N29+O29-G29>=0,N29+O29-G29,0) -> 0 | R29: =P29+Q29 -> 0 | S29: https://articulo.mercadolibre.cl/MLC-2855615494-fuente-de-agua-pileta-de-agua-buda-feng-shui-18-cm-con-luz-gris-_JM
A30: {=XLOOKUP(B30,Costos_Proveedores!$B$2:$B$2000,Costos_Proveedores!$A$2:$A$2000)} -> MULI | B30: MLC2855521002 | C30: 106551G | D30: Basurero Metálico Con Pedal 8 Litros Pedal Acabado Madera Color Gris | E30: paused | F30: 0 | G30: 0 | H30: =IF(I30="Sí",F30,F30+G30) -> 0 | I30: No | J30: =VLOOKUP(B30,Costos_Proveedores!$B$2:$J$1000,9,FALSE()) -> 8400 | K30: =IFERROR(H30*J30,0) -> 0 | P30: =IF(M30>=F30,M30-F30,0) -> 0 | Q30: =IF(N30+O30-G30>=0,N30+O30-G30,0) -> 0 | R30: =P30+Q30 -> 0 | S30: https://articulo.mercadolibre.cl/MLC-2855521002-basurero-metalico-con-pedal-8-litros-pedal-acabado-madera-color-gris-_JM
A31: {=XLOOKUP(B31,Costos_Proveedores!$B$2:$B$2000,Costos_Proveedores!$A$2:$A$2000)} -> MULI | B31: MLC1585279801 | C31: WF33311 | D31: Estatua Buda Pileta De Agua Fuente De Agua Buda 28cm Con Luz Gris | E31: paused | F31: 0 | G31: 0 | H31: =IF(I31="Sí",F31,F31+G31) -> 0 | I31: No | J31: =VLOOKUP(B31,Costos_Proveedores!$B$2:$J$1000,9,FALSE()) -> 12600 | K31: =IFERROR(H31*J31,0) -> 0 | P31: =IF(M31>=F31,M31-F31,0) -> 0 | Q31: =IF(N31+O31-G31>=0,N31+O31-G31,0) -> 0 | R31: =P31+Q31 -> 0 | S31: https://articulo.mercadolibre.cl/MLC-1585279801-estatua-buda-pileta-de-agua-fuente-de-agua-buda-28cm-con-luz-gris-_JM
A32: {=XLOOKUP(B32,Costos_Proveedores!$B$2:$B$2000,Costos_Proveedores!$A$2:$A$2000)} -> MULI | B32: MLC1585279683 | C32: 105651 | D32: Colgante De Viento Campana De Viento Llamador De Angel 68cm Plateado | E32: active | F32: 2 | G32: 0 | H32: =IF(I32="Sí",F32,F32+G32) -> 2 | I32: No | J32: =VLOOKUP(B32,Costos_Proveedores!$B$2:$J$1000,9,FALSE()) -> 2730 | K32: =IFERROR(H32*J32,0) -> 5460 | L32: 4 | M32: 4 | N32: 0 | O32: 0 | P32: =IF(M32>=F32,M32-F32,0) -> 2 | Q32: =IF(N32+O32-G32>=0,N32+O32-G32,0) -> 0 | R32: =P32+Q32 -> 2 | S32: https://articulo.mercadolibre.cl/MLC-1585279683-colgante-de-viento-campana-de-viento-llamador-de-angel-68cm-plateado-_JM
A33: {=XLOOKUP(B33,Costos_Proveedores!$B$2:$B$2000,Costos_Proveedores!$A$2:$A$2000)} -> MULI | B33: MLC1585189105 | C33: 105650 | D33: Colgante De Viento Campana De Viento Llamador De Angel Turco Plateado | E33: active | F33: 3 | G33: 0 | H33: =IF(I33="Sí",F33,F33+G33) -> 3 | I33: No | J33: =VLOOKUP(B33,Costos_Proveedores!$B$2:$J$1000,9,FALSE()) -> 2030 | K33: =IFERROR(H33*J33,0) -> 6090 | L33: 1 | M33: 0 | N33: 0 | O33: 1 | P33: =IF(M33>=F33,M33-F33,0) -> 0 | Q33: =IF(N33+O33-G33>=0,N33+O33-G33,0) -> 1 | R33: =P33+Q33 -> 1 | S33: https://articulo.mercadolibre.cl/MLC-1585189105-colgante-de-viento-campana-de-viento-llamador-de-angel-turco-plateado-_JM
A34: {=XLOOKUP(B34,Costos_Proveedores!$B$2:$B$2000,Costos_Proveedores!$A$2:$A$2000)} -> MULI | B34: MLC1585173079 | C34: BM22104 | D34: Figura Estatua Adorno Caballo Blanco Grande 29 Cm Elegante Blanco | E34: paused | G34: 0 | H34: =IF(I34="Sí",F34,F34+G34) -> 0 | I34: No | J34: =VLOOKUP(B34,Costos_Proveedores!$B$2:$J$1000,9,FALSE()) -> 11760 | K34: =IFERROR(H34*J34,0) -> 0 | P34: =IF(M34>=F34,M34-F34,0) -> 0 | Q34: =IF(N34+O34-G34>=0,N34+O34-G34,0) -> 0 | R34: =P34+Q34 -> 0 | S34: https://articulo.mercadolibre.cl/MLC-1585173079-figura-estatua-adorno-caballo-blanco-grande-29-cm-elegante-blanco-_JM
A35: {=XLOOKUP(B35,Costos_Proveedores!$B$2:$B$2000,Costos_Proveedores!$A$2:$A$2000)} -> MULI | B35: MLC1585111423 | C35: 107093 | D35: Caja 48 Tazones Para Sublimacion Blanco Grado A 11oz Ceramic Blanco | E35: paused | G35: 0 | H35: =IF(I35="Sí",F35,F35+G35) -> 0 | I35: No | J35: =VLOOKUP(B35,Costos_Proveedores!$B$2:$J$1000,9,FALSE()) -> 26208 | K35: =IFERROR(H35*J35,0) -> 0 | P35: =IF(M35>=F35,M35-F35,0) -> 0 | Q35: =IF(N35+O35-G35>=0,N35+O35-G35,0) -> 0 | R35: =P35+Q35 -> 0 | S35: https://articulo.mercadolibre.cl/MLC-1585111423-caja-48-tazones-para-sublimacion-blanco-grado-a-11oz-ceramic-blanco-_JM
A36: {=XLOOKUP(B36,Costos_Proveedores!$B$2:$B$2000,Costos_Proveedores!$A$2:$A$2000)} -> MULI | B36: MLC1585098747 | C36: WF33374 | D36: Estatua Decorativa Pileta De Agua Fuente De Agua Grande 40cm Gris | E36: paused | G36: 0 | H36: =IF(I36="Sí",F36,F36+G36) -> 0 | I36: No | J36: =VLOOKUP(B36,Costos_Proveedores!$B$2:$J$1000,9,FALSE()) -> 16800 | K36: =IFERROR(H36*J36,0) -> 0 | P36: =IF(M36>=F36,M36-F36,0) -> 0 | Q36: =IF(N36+O36-G36>=0,N36+O36-G36,0) -> 0 | R36: =P36+Q36 -> 0 | S36: https://articulo.mercadolibre.cl/MLC-1585098747-estatua-decorativa-pileta-de-agua-fuente-de-agua-grande-40cm-gris-_JM
A37: {=XLOOKUP(B37,Costos_Proveedores!$B$2:$B$2000,Costos_Proveedores!$A$2:$A$2000)} -> MULI | B37: MLC1585094821 | C37: 105741 | D37: Set Jarra Y 6 Vasos Conjunto Jarra 2 Litros 6 Vasos Vidrio Transparente | E37: paused | F37: 0 | G37: 0 | H37: =IF(I37="Sí",F37,F37+G37) -> 0 | I37: No | J37: =VLOOKUP(B37,Costos_Proveedores!$B$2:$J$1000,9,FALSE()) -> 7560 | K37: =IFERROR(H37*J37,0) -> 0 | L37: 3 | M37: 3 | N37: 0 | O37: 0 | P37: =IF(M37>=F37,M37-F37,0) -> 3 | Q37: =IF(N37+O37-G37>=0,N37+O37-G37,0) -> 0 | R37: =P37+Q37 -> 3 | S37: https://articulo.mercadolibre.cl/MLC-1585094821-set-jarra-y-6-vasos-conjunto-jarra-2-litros-6-vasos-vidrio-transparente-_JM
A38: {=XLOOKUP(B38,Costos_Proveedores!$B$2:$B$2000,Costos_Proveedores!$A$2:$A$2000)} -> MULI | B38: MLC1585093281 | C38: 105493 | D38: Separador De Servicios Organizador De Servicios O Cubiertos Blanco | E38: paused | F38: 0 | G38: 0 | H38: =IF(I38="Sí",F38,F38+G38) -> 0 | I38: No | J38: =VLOOKUP(B38,Costos_Proveedores!$B$2:$J$1000,9,FALSE()) -> $ 756 | K38: =IFERROR(H38*J38,0) -> 0 | L38: 25 | M38: 20 | N38: 0 | O38: 0 | P38: =IF(M38>=F38,M38-F38,0) -> 20 | Q38: =IF(N38+O38-G38>=0,N38+O38-G38,0) -> 0 | R38: =P38+Q38 -> 20 | S38: https://articulo.mercadolibre.cl/MLC-1585093281-separador-de-servicios-organizador-de-servicios-o-cubiertos-blanco-_JM
A39: {=XLOOKUP(B39,Costos_Proveedores!$B$2:$B$2000,Costos_Proveedores!$A$2:$A$2000)} -> MULI | B39: MLC2856205088 | C39: BM22183 | D39: Estatua Figura Gato Adorno Interior Gata Regalo 30 Cm Blanco | E39: paused | F39: 0 | G39: 0 | H39: =IF(I39="Sí",F39,F39+G39) -> 0 | I39: No | J39: =VLOOKUP(B39,Costos_Proveedores!$B$2:$J$1000,9,FALSE()) -> 6300 | K39: =IFERROR(H39*J39,0) -> 0 | L39: 1 | M39: 1 | N39: 0 | O39: 0 | P39: =IF(M39>=F39,M39-F39,0) -> 1 | Q39: =IF(N39+O39-G39>=0,N39+O39-G39,0) -> 0 | R39: =P39+Q39 -> 1 | S39: https://articulo.mercadolibre.cl/MLC-2856205088-estatua-figura-gato-adorno-interior-gata-regalo-30-cm-blanco-_JM
A40: {=XLOOKUP(B40,Costos_Proveedores!$B$2:$B$2000,Costos_Proveedores!$A$2:$A$2000)} -> MULI | B40: MLC2855996872 | C40: RS66888 | D40: Estatua Dama De La Justicia Adorno Dama De La Justicia Plateado | E40: paused | F40: 0 | G40: 0 | H40: =IF(I40="Sí",F40,F40+G40) -> 0 | I40: No | J40: =VLOOKUP(B40,Costos_Proveedores!$B$2:$J$1000,9,FALSE()) -> 11760 | K40: =IFERROR(H40*J40,0) -> 0 | L40: 3 | M40: 3 | N40: 0 | O40: 0 | P40: =IF(M40>=F40,M40-F40,0) -> 3 | Q40: =IF(N40+O40-G40>=0,N40+O40-G40,0) -> 0 | R40: =P40+Q40 -> 3 | S40: https://articulo.mercadolibre.cl/MLC-2855996872-estatua-dama-de-la-justicia-adorno-dama-de-la-justicia-plateado-_JM
A41: {=XLOOKUP(B41,Costos_Proveedores!$B$2:$B$2000,Costos_Proveedores!$A$2:$A$2000)} -> MULI | B41: MLC2856788222 | C41: WF33377 | D41: Fuente De Agua Pileta De Agua 3 Vasijas Grande 37 Cm Con Luz Gris | E41: paused | G41: 0 | H41: =IF(I41="Sí",F41,F41+G41) -> 0 | I41: No | J41: =VLOOKUP(B41,Costos_Proveedores!$B$2:$J$1000,9,FALSE()) -> 16800 | K41: =IFERROR(H41*J41,0) -> 0 | P41: =IF(M41>=F41,M41-F41,0) -> 0 | Q41: =IF(N41+O41-G41>=0,N41+O41-G41,0) -> 0 | R41: =P41+Q41 -> 0 | S41: https://articulo.mercadolibre.cl/MLC-2856788222-fuente-de-agua-pileta-de-agua-3-vasijas-grande-37-cm-con-luz-gris-_JM
A42: {=XLOOKUP(B42,Costos_Proveedores!$B$2:$B$2000,Costos_Proveedores!$A$2:$A$2000)} -> MULI | B42: MLC1586344127 | C42: WF33328 | D42: Fuente De Agua Pileta De Agua Ganesha Con Luz 18 Cm Dorado | E42: active | F42: 0 | G42: 2 | H42: =IF(I42="Sí",F42,F42+G42) -> 2 | I42: No | J42: =VLOOKUP(B42,Costos_Proveedores!$B$2:$J$1000,9,FALSE()) -> 5880 | K42: =IFERROR(H42*J42,0) -> 11760 | P42: =IF(M42>=F42,M42-F42,0) -> 0 | Q42: =IF(N42+O42-G42>=0,N42+O42-G42,0) -> 0 | R42: =P42+Q42 -> 0 | S42: https://articulo.mercadolibre.cl/MLC-1586344127-fuente-de-agua-pileta-de-agua-ganesha-con-luz-18-cm-dorado-_JM
A43: {=XLOOKUP(B43,Costos_Proveedores!$B$2:$B$2000,Costos_Proveedores!$A$2:$A$2000)} -> MULI | B43: MLC1586318489 | C43: WF33338 | D43: Fuente De Agua Pileta De Agua Jesus Sagrado Con Luz 18 Cm Gris | E43: paused | F43: 0 | G43: 0 | H43: =IF(I43="Sí",F43,F43+G43) -> 0 | I43: No | J43: =VLOOKUP(B43,Costos_Proveedores!$B$2:$J$1000,9,FALSE()) -> 5880 | K43: =IFERROR(H43*J43,0) -> 0 | P43: =IF(M43>=F43,M43-F43,0) -> 0 | Q43: =IF(N43+O43-G43>=0,N43+O43-G43,0) -> 0 | R43: =P43+Q43 -> 0 | S43: https://articulo.mercadolibre.cl/MLC-1586318489-fuente-de-agua-pileta-de-agua-jesus-sagrado-con-luz-18-cm-gris-_JM
A44: {=XLOOKUP(B44,Costos_Proveedores!$B$2:$B$2000,Costos_Proveedores!$A$2:$A$2000)} -> MULI | B44: MLC1586264401 | C44: WF33353 | D44: Fuente De Agua Pileta De Agua Elefantes 28 Cm Con Luz Gris | E44: paused | F44: 0 | G44: 0 | H44: =IF(I44="Sí",F44,F44+G44) -> 0 | I44: No | J44: =VLOOKUP(B44,Costos_Proveedores!$B$2:$J$1000,9,FALSE()) -> 16800 | K44: =IFERROR(H44*J44,0) -> 0 | P44: =IF(M44>=F44,M44-F44,0) -> 0 | Q44: =IF(N44+O44-G44>=0,N44+O44-G44,0) -> 0 | R44: =P44+Q44 -> 0 | S44: https://articulo.mercadolibre.cl/MLC-1586264401-fuente-de-agua-pileta-de-agua-elefantes-28-cm-con-luz-gris-_JM
A45: {=XLOOKUP(B45,Costos_Proveedores!$B$2:$B$2000,Costos_Proveedores!$A$2:$A$2000)} -> MULI | B45: MLC1586204807 | C45: YQ102251 | D45: Fuente De Agua Pileta De Agua Querubín 18cm Con Luz Gris | E45: paused | F45: 0 | G45: 0 | H45: =IF(I45="Sí",F45,F45+G45) -> 0 | I45: No | J45: =VLOOKUP(B45,Costos_Proveedores!$B$2:$J$1000,9,FALSE()) -> 6300 | K45: =IFERROR(H45*J45,0) -> 0 | P45: =IF(M45>=F45,M45-F45,0) -> 0 | Q45: =IF(N45+O45-G45>=0,N45+O45-G45,0) -> 0 | R45: =P45+Q45 -> 0 | S45: https://articulo.mercadolibre.cl/MLC-1586204807-fuente-de-agua-pileta-de-agua-querubin-18cm-con-luz-gris-_JM
A46: {=XLOOKUP(B46,Costos_Proveedores!$B$2:$B$2000,Costos_Proveedores!$A$2:$A$2000)} -> MULI | B46: MLC1586176079 | C46: WF33336 | D46: Fuente De Agua Pileta De Agua Elefante Con Luz 18 Cm Gris | E46: paused | F46: 0 | G46: 0 | H46: =IF(I46="Sí",F46,F46+G46) -> 0 | I46: No | J46: =VLOOKUP(B46,Costos_Proveedores!$B$2:$J$1000,9,FALSE()) -> 5580 | K46: =IFERROR(H46*J46,0) -> 0 | P46: =IF(M46>=F46,M46-F46,0) -> 0 | Q46: =IF(N46+O46-G46>=0,N46+O46-G46,0) -> 0 | R46: =P46+Q46 -> 0 | S46: https://articulo.mercadolibre.cl/MLC-1586176079-fuente-de-agua-pileta-de-agua-elefante-con-luz-18-cm-gris-_JM
A47: {=XLOOKUP(B47,Costos_Proveedores!$B$2:$B$2000,Costos_Proveedores!$A$2:$A$2000)} -> MULI | B47: MLC1585891979 | C47: FH49021 | D47: Estatua Figura Religiosa Angel Virgen Maria Familia Sagrada Roble | E47: paused | F47: 0 | G47: 0 | H47: =IF(I47="Sí",F47,F47+G47) -> 0 | I47: No | J47: =VLOOKUP(B47,Costos_Proveedores!$B$2:$J$1000,9,FALSE()) -> 9240 | K47: =IFERROR(H47*J47,0) -> 0 | P47: =IF(M47>=F47,M47-F47,0) -> 0 | Q47: =IF(N47+O47-G47>=0,N47+O47-G47,0) -> 0 | R47: =P47+Q47 -> 0 | S47: https://articulo.mercadolibre.cl/MLC-1585891979-estatua-figura-religiosa-angel-virgen-maria-familia-sagrada-roble-_JM
A48: {=XLOOKUP(B48,Costos_Proveedores!$B$2:$B$2000,Costos_Proveedores!$A$2:$A$2000)} -> MULI | B48: MLC2857327110 | C48: WF33327 | D48: Fuente De Agua Pileta De Agua Ganesha Interior 18cm Con Luz Dorado | E48: paused | F48: 0 | G48: 0 | H48: =IF(I48="Sí",F48,F48+G48) -> 0 | I48: No | J48: =VLOOKUP(B48,Costos_Proveedores!$B$2:$J$1000,9,FALSE()) -> 5880 | K48: =IFERROR(H48*J48,0) -> 0 | L48: 5 | M48: 1 | N48: 4 | O48: 0 | P48: =IF(M48>=F48,M48-F48,0) -> 1 | Q48: =IF(N48+O48-G48>=0,N48+O48-G48,0) -> 4 | R48: =P48+Q48 -> 5 | S48: https://articulo.mercadolibre.cl/MLC-2857327110-fuente-de-agua-pileta-de-agua-ganesha-interior-18cm-con-luz-dorado-_JM
A49: {=XLOOKUP(B49,Costos_Proveedores!$B$2:$B$2000,Costos_Proveedores!$A$2:$A$2000)} -> MULI | B49: MLC2857300512 | C49: WF33375 | D49: Fuente De Agua Pileta De Agua Elefantes Grande 37 Cm Con Luz Gris | E49: paused | G49: 0 | H49: =IF(I49="Sí",F49,F49+G49) -> 0 | I49: No | J49: =VLOOKUP(B49,Costos_Proveedores!$B$2:$J$1000,9,FALSE()) -> 16800 | K49: =IFERROR(H49*J49,0) -> 0 | P49: =IF(M49>=F49,M49-F49,0) -> 0 | Q49: =IF(N49+O49-G49>=0,N49+O49-G49,0) -> 0 | R49: =P49+Q49 -> 0 | S49: https://articulo.mercadolibre.cl/MLC-2857300512-fuente-de-agua-pileta-de-agua-elefantes-grande-37-cm-con-luz-gris-_JM
A50: {=XLOOKUP(B50,Costos_Proveedores!$B$2:$B$2000,Costos_Proveedores!$A$2:$A$2000)} -> MULI | B50: MLC1589044173 | C50: 107175 | D50: Pack 4 Goma Eva Piso Alfombra Antigolpes 50x50x1cm Multicolor Liso | E50: paused | F50: 0 | G50: 0 | H50: =IF(I50="Sí",F50,F50+G50) -> 0 | I50: No | J50: =VLOOKUP(B50,Costos_Proveedores!$B$2:$J$1000,9,FALSE()) -> 2730 | K50: =IFERROR(H50*J50,0) -> 0 | P50: =IF(M50>=F50,M50-F50,0) -> 0 | Q50: =IF(N50+O50-G50>=0,N50+O50-G50,0) -> 0 | R50: =P50+Q50 -> 0 | S50: https://articulo.mercadolibre.cl/MLC-1589044173-pack-4-goma-eva-piso-alfombra-antigolpes-50x50x1cm-multicolor-liso-_JM
A51: {=XLOOKUP(B51,Costos_Proveedores!$B$2:$B$2000,Costos_Proveedores!$A$2:$A$2000)} -> MULI | B51: MLC1589018163 | C51: 105007 | D51: Naipe Ingles Cartas Inglesa Baraja Ingles Plastificado Poker Multicolor Inglés | E51: paused | F51: 0 | G51: 0 | H51: =IF(I51="Sí",F51,F51+G51) -> 0 | I51: No | J51: =VLOOKUP(B51,Costos_Proveedores!$B$2:$J$1000,9,FALSE()) -> $ 456 | K51: =IFERROR(H51*J51,0) -> 0 | P51: =IF(M51>=F51,M51-F51,0) -> 0 | Q51: =IF(N51+O51-G51>=0,N51+O51-G51,0) -> 0 | R51: =P51+Q51 -> 0 | S51: https://articulo.mercadolibre.cl/MLC-1589018163-naipe-ingles-cartas-inglesa-baraja-ingles-plastificado-poker-multicolor-ingles-_JM
A52: {=XLOOKUP(B52,Costos_Proveedores!$B$2:$B$2000,Costos_Proveedores!$A$2:$A$2000)} -> MULI | B52: MLC1590158569 | C52: WF33337 | D52: Fuente De Agua Pileta De Agua Virgen Maria Con Luz 18 Cm Gris | E52: paused | F52: 0 | G52: 0 | H52: =IF(I52="Sí",F52,F52+G52) -> 0 | I52: No | J52: =VLOOKUP(B52,Costos_Proveedores!$B$2:$J$1000,9,FALSE()) -> 5880 | K52: =IFERROR(H52*J52,0) -> 0 | L52: 1 | M52: 1 | N52: 0 | O52: 0 | P52: =IF(M52>=F52,M52-F52,0) -> 1 | Q52: =IF(N52+O52-G52>=0,N52+O52-G52,0) -> 0 | R52: =P52+Q52 -> 1 | S52: https://articulo.mercadolibre.cl/MLC-1590158569-fuente-de-agua-pileta-de-agua-virgen-maria-con-luz-18-cm-gris-_JM
A53: {=XLOOKUP(B53,Costos_Proveedores!$B$2:$B$2000,Costos_Proveedores!$A$2:$A$2000)} -> MULI | B53: MLC1590145681 | C53: 103367 | D53: Basurero Metálico Con Pedal 5 Litros Plateado Acero Canasta | E53: paused | F53: 0 | G53: 0 | H53: =IF(I53="Sí",F53,F53+G53) -> 0 | I53: No | J53: =VLOOKUP(B53,Costos_Proveedores!$B$2:$J$1000,9,FALSE()) -> 4550 | K53: =IFERROR(H53*J53,0) -> 0 | P53: =IF(M53>=F53,M53-F53,0) -> 0 | Q53: =IF(N53+O53-G53>=0,N53+O53-G53,0) -> 0 | R53: =P53+Q53 -> 0 | S53: https://articulo.mercadolibre.cl/MLC-1590145681-basurero-metalico-con-pedal-5-litros-plateado-acero-canasta-_JM
A54: {=XLOOKUP(B54,Costos_Proveedores!$B$2:$B$2000,Costos_Proveedores!$A$2:$A$2000)} -> MULI | B54: MLC1589095741 | C54: 58484 | D54: Set 3 Maletas De Viaje 23, 15, 10 Kg Maleta De Cabina Tela Marrón Marron Elegante | E54: paused | G54: 0 | H54: =IF(I54="Sí",F54,F54+G54) -> 0 | I54: No | J54: =VLOOKUP(B54,Costos_Proveedores!$B$2:$J$1000,9,FALSE()) -> 40700 | K54: =IFERROR(H54*J54,0) -> 0 | P54: =IF(M54>=F54,M54-F54,0) -> 0 | Q54: =IF(N54+O54-G54>=0,N54+O54-G54,0) -> 0 | R54: =P54+Q54 -> 0 | S54: https://articulo.mercadolibre.cl/MLC-1589095741-set-3-maletas-de-viaje-23-15-10-kg-maleta-de-cabina-tela-marron-marron-elegante-_JM
A55: {=XLOOKUP(B55,Costos_Proveedores!$B$2:$B$2000,Costos_Proveedores!$A$2:$A$2000)} -> MULI | B55: MLC2863379684 | C55: ML235 | D55: Set 10 30x30 Alfombra Infantil Goma Eva Cuadros Bebes Niños Color Multicolor Números | E55: paused | F55: 0 | G55: 0 | H55: =IF(I55="Sí",F55,F55+G55) -> 0 | I55: No | J55: =VLOOKUP(B55,Costos_Proveedores!$B$2:$J$1000,9,FALSE()) -> 2730 | K55: =IFERROR(H55*J55,0) -> 0 | P55: =IF(M55>=F55,M55-F55,0) -> 0 | Q55: =IF(N55+O55-G55>=0,N55+O55-G55,0) -> 0 | R55: =P55+Q55 -> 0 | S55: https://articulo.mercadolibre.cl/MLC-2863379684-set-10-30x30-alfombra-infantil-goma-eva-cuadros-bebes-ninos-color-multicolor-numeros-_JM
A56: {=XLOOKUP(B56,Costos_Proveedores!$B$2:$B$2000,Costos_Proveedores!$A$2:$A$2000)} -> MULI | B56: MLC1593130463 | C56: ML331 | D56: Set 10 30x30 Alfombra Infantil Goma Eva Cuadros Bebes Niños Color Multicolor Liso | E56: paused | F56: 0 | G56: 0 | H56: =IF(I56="Sí",F56,F56+G56) -> 0 | I56: No | J56: =VLOOKUP(B56,Costos_Proveedores!$B$2:$J$1000,9,FALSE()) -> 2730 | K56: =IFERROR(H56*J56,0) -> 0 | P56: =IF(M56>=F56,M56-F56,0) -> 0 | Q56: =IF(N56+O56-G56>=0,N56+O56-G56,0) -> 0 | R56: =P56+Q56 -> 0 | S56: https://articulo.mercadolibre.cl/MLC-1593130463-set-10-30x30-alfombra-infantil-goma-eva-cuadros-bebes-ninos-color-multicolor-liso-_JM
A57: {=XLOOKUP(B57,Costos_Proveedores!$B$2:$B$2000,Costos_Proveedores!$A$2:$A$2000)} -> MULI | B57: MLC2867073664 | C57: ML236 | D57: Set 10 30x30 Alfombra Infantil Goma Eva Cuadros Bebes Niños Color Multicolor Letras | E57: paused | F57: 0 | G57: 0 | H57: =IF(I57="Sí",F57,F57+G57) -> 0 | I57: No | J57: =VLOOKUP(B57,Costos_Proveedores!$B$2:$J$1000,9,FALSE()) -> 2730 | K57: =IFERROR(H57*J57,0) -> 0 | P57: =IF(M57>=F57,M57-F57,0) -> 0 | Q57: =IF(N57+O57-G57>=0,N57+O57-G57,0) -> 0 | R57: =P57+Q57 -> 0 | S57: https://articulo.mercadolibre.cl/MLC-2867073664-set-10-30x30-alfombra-infantil-goma-eva-cuadros-bebes-ninos-color-multicolor-letras-_JM
A58: {=XLOOKUP(B58,Costos_Proveedores!$B$2:$B$2000,Costos_Proveedores!$A$2:$A$2000)} -> MULI | B58: MLC2869353570 | C58: 106958 | D58: La Última Cena Jesus Figura Decorativa Religiosa Adorno Marrón | E58: active | F58: 2 | G58: 0 | H58: =IF(I58="Sí",F58,F58+G58) -> 2 | I58: No | J58: =VLOOKUP(B58,Costos_Proveedores!$B$2:$J$1000,9,FALSE()) -> 9800 | K58: =IFERROR(H58*J58,0) -> 19600 | L58: 2 | M58: 2 | N58: 0 | O58: 0 | P58: =IF(M58>=F58,M58-F58,0) -> 0 | Q58: =IF(N58+O58-G58>=0,N58+O58-G58,0) -> 0 | R58: =P58+Q58 -> 0 | S58: https://articulo.mercadolibre.cl/MLC-2869353570-la-ultima-cena-jesus-figura-decorativa-religiosa-adorno-marron-_JM
A59: {=XLOOKUP(B59,Costos_Proveedores!$B$2:$B$2000,Costos_Proveedores!$A$2:$A$2000)} -> MULI | B59: MLC1596422757 | C59: 104996 | D59: Naipe Ingles Cartas Inglesa Baraja Ingles Plastificado Poker Multicolor Inglés | E59: paused | F59: 0 | G59: 0 | H59: =IF(I59="Sí",F59,F59+G59) -> 0 | I59: No | J59: =VLOOKUP(B59,Costos_Proveedores!$B$2:$J$1000,9,FALSE()) -> 1260 | K59: =IFERROR(H59*J59,0) -> 0 | P59: =IF(M59>=F59,M59-F59,0) -> 0 | Q59: =IF(N59+O59-G59>=0,N59+O59-G59,0) -> 0 | R59: =P59+Q59 -> 0 | S59: https://articulo.mercadolibre.cl/MLC-1596422757-naipe-ingles-cartas-inglesa-baraja-ingles-plastificado-poker-multicolor-ingles-_JM
A60: {=XLOOKUP(B60,Costos_Proveedores!$B$2:$B$2000,Costos_Proveedores!$A$2:$A$2000)} -> EXTREMO SUR | B60: MLC2870456220 | C60: 7804651160358 | D60: L-treonato De Magnesio 500mg 90 Cápsulas 100% Natural Extrem Sin Sabor | E60: paused | F60: 0 | G60: 0 | H60: =IF(I60="Sí",F60,F60+G60) -> 0 | I60: No | J60: =VLOOKUP(B60,Costos_Proveedores!$B$2:$J$1000,9,FALSE()) -> 6218 | K60: =IFERROR(H60*J60,0) -> 0 | P60: =IF(M60>=F60,M60-F60,0) -> 0 | Q60: =IF(N60+O60-G60>=0,N60+O60-G60,0) -> 0 | R60: =P60+Q60 -> 0 | S60: https://articulo.mercadolibre.cl/MLC-2870456220-l-treonato-de-magnesio-500mg-90-capsulas-100-natural-extrem-sin-sabor-_JM
A61: {=XLOOKUP(B61,Costos_Proveedores!$B$2:$B$2000,Costos_Proveedores!$A$2:$A$2000)} -> EXTREMO SUR | B61: MLC2870456002 | C61: 7896108058967 | D61: Zma Zinc + Magnesio + Vit B6 90 Capsulas 500mg Sabor Sin Sabor | E61: paused | F61: 0 | G61: 84 | H61: =IF(I61="Sí",F61,F61+G61) -> 0 | I61: Sí | J61: =VLOOKUP(B61,Costos_Proveedores!$B$2:$J$1000,9,FALSE()) -> 3392 | K61: =IFERROR(H61*J61,0) -> 0 | P61: =IF(M61>=F61,M61-F61,0) -> 0 | Q61: =IF(N61+O61-G61>=0,N61+O61-G61,0) -> 0 | R61: =P61+Q61 -> 0 | S61: https://articulo.mercadolibre.cl/MLC-2870456002-zma-zinc-magnesio-vit-b6-90-capsulas-500mg-sabor-sin-sabor-_JM
A62: {=XLOOKUP(B62,Costos_Proveedores!$B$2:$B$2000,Costos_Proveedores!$A$2:$A$2000)} -> EXTREMO SUR | B62: MLC2870455538 | C62: 7804651160211 | D62: Biotina + Colágeno Hidrolizado | E62: paused | F62: 0 | G62: 1 | H62: =IF(I62="Sí",F62,F62+G62) -> 0 | I62: Sí | J62: =VLOOKUP(B62,Costos_Proveedores!$B$2:$J$1000,9,FALSE()) -> 3392 | K62: =IFERROR(H62*J62,0) -> 0 | P62: =IF(M62>=F62,M62-F62,0) -> 0 | Q62: =IF(N62+O62-G62>=0,N62+O62-G62,0) -> 0 | R62: =P62+Q62 -> 0 | S62: https://articulo.mercadolibre.cl/MLC-2870455538-biotina-colageno-hidrolizado-_JM
A63: {=XLOOKUP(B63,Costos_Proveedores!$B$2:$B$2000,Costos_Proveedores!$A$2:$A$2000)} -> EXTREMO SUR | B63: MLC2870432286 | C63: Pack2Bisglicinato | D63: 2 Bisglicinato De Magnesio 500mg X 60 Caps Vegetal Sabor Neutro | E63: paused | F63: 0 | G63: 1 | H63: =IF(I63="Sí",F63,F63+G63) -> 0 | I63: Sí | J63: =VLOOKUP(B63,Costos_Proveedores!$B$2:$J$1000,9,FALSE()) -> 9044 | K63: =IFERROR(H63*J63,0) -> 0 | P63: =IF(M63>=F63,M63-F63,0) -> 0 | Q63: =IF(N63+O63-G63>=0,N63+O63-G63,0) -> 0 | R63: =P63+Q63 -> 0 | S63: https://articulo.mercadolibre.cl/MLC-2870432286-2-bisglicinato-de-magnesio-500mg-x-60-caps-vegetal-sabor-neutro-_JM
A64: {=XLOOKUP(B64,Costos_Proveedores!$B$2:$B$2000,Costos_Proveedores!$A$2:$A$2000)} -> EXTREMO SUR | B64: MLC2870432226 | C64: Pack3MagMalatoEX | D64: Pack De 3 Magnesio Malato 500mg 180 Cápsulas Vegetales Sabor Natural | E64: paused | F64: 0 | G64: 0 | H64: =IF(I64="Sí",F64,F64+G64) -> 0 | I64: Sí | J64: =VLOOKUP(B64,Costos_Proveedores!$B$2:$J$1000,9,FALSE()) -> 13566 | K64: =IFERROR(H64*J64,0) -> 0 | P64: =IF(M64>=F64,M64-F64,0) -> 0 | Q64: =IF(N64+O64-G64>=0,N64+O64-G64,0) -> 0 | R64: =P64+Q64 -> 0 | S64: https://articulo.mercadolibre.cl/MLC-2870432226-pack-de-3-magnesio-malato-500mg-180-capsulas-vegetales-sabor-natural-_JM
A65: {=XLOOKUP(B65,Costos_Proveedores!$B$2:$B$2000,Costos_Proveedores!$A$2:$A$2000)} -> EXTREMO SUR | B65: MLC2870367928 | C65: 7804651160310 | D65: Citrato De Magnesio Cápsulas Extremo Sur Sin Sabor Libre De Gluten Vegano 45g | E65: paused | G65: 1 | H65: =IF(I65="Sí",F65,F65+G65) -> 1 | I65: No | J65: =VLOOKUP(B65,Costos_Proveedores!$B$2:$J$1000,9,FALSE()) -> 10175 | K65: =IFERROR(H65*J65,0) -> 10175 | P65: =IF(M65>=F65,M65-F65,0) -> 0 | Q65: =IF(N65+O65-G65>=0,N65+O65-G65,0) -> 0 | R65: =P65+Q65 -> 0 | S65: https://articulo.mercadolibre.cl/MLC-2870367928-citrato-de-magnesio-capsulas-extremo-sur-sin-sabor-libre-de-gluten-vegano-45g-_JM
A66: {=XLOOKUP(B66,Costos_Proveedores!$B$2:$B$2000,Costos_Proveedores!$A$2:$A$2000)} -> EXTREMO SUR | B66: MLC2870367566 | C66: 7804651160211-1 | D66: Biotina + Colágeno Hidrolizado Con Vitamina C Extremo Sur Sin Sabor | E66: paused | F66: 0 | G66: 1 | H66: =IF(I66="Sí",F66,F66+G66) -> 0 | I66: Sí | J66: =VLOOKUP(B66,Costos_Proveedores!$B$2:$J$1000,9,FALSE()) -> 3392 | K66: =IFERROR(H66*J66,0) -> 0 | P66: =IF(M66>=F66,M66-F66,0) -> 0 | Q66: =IF(N66+O66-G66>=0,N66+O66-G66,0) -> 0 | R66: =P66+Q66 -> 0 | S66: https://articulo.mercadolibre.cl/MLC-2870367566-biotina-colageno-hidrolizado-con-vitamina-c-extremo-sur-sin-sabor-_JM
A67: {=XLOOKUP(B67,Costos_Proveedores!$B$2:$B$2000,Costos_Proveedores!$A$2:$A$2000)} -> EXTREMO SUR | B67: MLC2870329548 | C67: 7896108058967-1 | D67: Zma Zinc + Magnesio + Vit B6 90 Capsulas 500mg Sabor Sin Sab Sin Sabor | E67: paused | F67: 0 | G67: 84 | H67: =IF(I67="Sí",F67,F67+G67) -> 0 | I67: Sí | J67: =VLOOKUP(B67,Costos_Proveedores!$B$2:$J$1000,9,FALSE()) -> 3392 | K67: =IFERROR(H67*J67,0) -> 0 | P67: =IF(M67>=F67,M67-F67,0) -> 0 | Q67: =IF(N67+O67-G67>=0,N67+O67-G67,0) -> 0 | R67: =P67+Q67 -> 0 | S67: https://articulo.mercadolibre.cl/MLC-2870329548-zma-zinc-magnesio-vit-b6-90-capsulas-500mg-sabor-sin-sab-sin-sabor-_JM
A68: {=XLOOKUP(B68,Costos_Proveedores!$B$2:$B$2000,Costos_Proveedores!$A$2:$A$2000)} -> EXTREMO SUR | B68: MLC2870329358 | C68: Pack2Mag-Cit | D68: Pack 2 Magnesio Citrato 180 Cap Y 2 Potasio Citrato 180 Cap Extremo Sur | E68: paused | F68: 0 | G68: 100 | H68: =IF(I68="Sí",F68,F68+G68) -> 0 | I68: Sí | J68: =VLOOKUP(B68,Costos_Proveedores!$B$2:$J$1000,9,FALSE()) -> 12436 | K68: =IFERROR(H68*J68,0) -> 0 | P68: =IF(M68>=F68,M68-F68,0) -> 0 | Q68: =IF(N68+O68-G68>=0,N68+O68-G68,0) -> 0 | R68: =P68+Q68 -> 0 | S68: https://articulo.mercadolibre.cl/MLC-2870329358-pack-2-magnesio-citrato-180-cap-y-2-potasio-citrato-180-cap-extremo-sur-_JM
A69: {=XLOOKUP(B69,Costos_Proveedores!$B$2:$B$2000,Costos_Proveedores!$A$2:$A$2000)} -> EXTREMO SUR | B69: MLC2870277888 | C69: Pack3MagMalato | D69: Pack De 3 Magnesio Malato 500mg 180 Cápsulas Vegetales Sabor Natural | E69: paused | F69: 0 | G69: 0 | H69: =IF(I69="Sí",F69,F69+G69) -> 0 | I69: Sí | J69: =VLOOKUP(B69,Costos_Proveedores!$B$2:$J$1000,9,FALSE()) -> 13566 | K69: =IFERROR(H69*J69,0) -> 0 | P69: =IF(M69>=F69,M69-F69,0) -> 0 | Q69: =IF(N69+O69-G69>=0,N69+O69-G69,0) -> 0 | R69: =P69+Q69 -> 0 | S69: https://articulo.mercadolibre.cl/MLC-2870277888-pack-de-3-magnesio-malato-500mg-180-capsulas-vegetales-sabor-natural-_JM
A70: {=XLOOKUP(B70,Costos_Proveedores!$B$2:$B$2000,Costos_Proveedores!$A$2:$A$2000)} -> EXTREMO SUR | B70: MLC2870265058 | C70: 7804651160358 | D70: L-treonato De Magnesio 500mg 90 Cápsulas 100% Natural Extremo Sur | E70: paused | F70: 0 | G70: 0 | H70: =IF(I70="Sí",F70,F70+G70) -> 0 | J70: =VLOOKUP(B70,Costos_Proveedores!$B$2:$J$1000,9,FALSE()) -> 6218 | K70: =IFERROR(H70*J70,0) -> 0 | P70: =IF(M70>=F70,M70-F70,0) -> 0 | Q70: =IF(N70+O70-G70>=0,N70+O70-G70,0) -> 0 | R70: =P70+Q70 -> 0 | S70: https://articulo.mercadolibre.cl/MLC-2870265058-l-treonato-de-magnesio-500mg-90-capsulas-100-natural-extremo-sur-_JM
A71: {=XLOOKUP(B71,Costos_Proveedores!$B$2:$B$2000,Costos_Proveedores!$A$2:$A$2000)} -> EXTREMO SUR | B71: MLC2870228100 | C71: Pack2Mag-Citrato | D71: Pack 2 Magnesio Citrato 180 Cap Y 2 Potasio Citrato 180 Cap Sin Sabor | E71: paused | F71: 0 | G71: 100 | H71: =IF(I71="Sí",F71,F71+G71) -> 0 | I71: Sí | J71: =VLOOKUP(B71,Costos_Proveedores!$B$2:$J$1000,9,FALSE()) -> 12436 | K71: =IFERROR(H71*J71,0) -> 0 | P71: =IF(M71>=F71,M71-F71,0) -> 0 | Q71: =IF(N71+O71-G71>=0,N71+O71-G71,0) -> 0 | R71: =P71+Q71 -> 0 | S71: https://articulo.mercadolibre.cl/MLC-2870228100-pack-2-magnesio-citrato-180-cap-y-2-potasio-citrato-180-cap-sin-sabor-_JM
A72: {=XLOOKUP(B72,Costos_Proveedores!$B$2:$B$2000,Costos_Proveedores!$A$2:$A$2000)} -> EXTREMO SUR | B72: MLC1596962971 | C72: Pack2BisgliEX | D72: 2 Bisglicinato De Magnesio 500mg X 60 Caps Vegetal Sabor Neu Neutro | E72: paused | F72: 0 | G72: 1 | H72: =IF(I72="Sí",F72,F72+G72) -> 0 | I72: Sí | J72: =VLOOKUP(B72,Costos_Proveedores!$B$2:$J$1000,9,FALSE()) -> 9044 | K72: =IFERROR(H72*J72,0) -> 0 | P72: =IF(M72>=F72,M72-F72,0) -> 0 | Q72: =IF(N72+O72-G72>=0,N72+O72-G72,0) -> 0 | R72: =P72+Q72 -> 0 | S72: https://articulo.mercadolibre.cl/MLC-1596962971-2-bisglicinato-de-magnesio-500mg-x-60-caps-vegetal-sabor-neu-neutro-_JM
A73: {=XLOOKUP(B73,Costos_Proveedores!$B$2:$B$2000,Costos_Proveedores!$A$2:$A$2000)} -> EXTREMO SUR | B73: MLC1596924193 | C73: 7804651160310-1 | D73: Suplemento En Cápsula Extremo Sur Citrato De Magnesio X 45g Sin Sabor | E73: paused | G73: 1 | H73: =IF(I73="Sí",F73,F73+G73) -> 1 | I73: No | J73: =VLOOKUP(B73,Costos_Proveedores!$B$2:$J$1000,9,FALSE()) -> 3392 | K73: =IFERROR(H73*J73,0) -> 3392 | P73: =IF(M73>=F73,M73-F73,0) -> 0 | Q73: =IF(N73+O73-G73>=0,N73+O73-G73,0) -> 0 | R73: =P73+Q73 -> 0 | S73: https://articulo.mercadolibre.cl/MLC-1596924193-suplemento-en-capsula-extremo-sur-citrato-de-magnesio-x-45g-sin-sabor-_JM
A74: {=XLOOKUP(B74,Costos_Proveedores!$B$2:$B$2000,Costos_Proveedores!$A$2:$A$2000)} -> MULI | B74: MLC2872135864 | C74: TH21557 | D74: Bombonera Con Tapa Bombonera Para Bombones Ceramica Frutilla Rojo | E74: paused | G74: 0 | H74: =IF(I74="Sí",F74,F74+G74) -> 0 | I74: No | J74: =VLOOKUP(B74,Costos_Proveedores!$B$2:$J$1000,9,FALSE()) -> 5880 | K74: =IFERROR(H74*J74,0) -> 0 | P74: =IF(M74>=F74,M74-F74,0) -> 0 | Q74: =IF(N74+O74-G74>=0,N74+O74-G74,0) -> 0 | R74: =P74+Q74 -> 0 | S74: https://articulo.mercadolibre.cl/MLC-2872135864-bombonera-con-tapa-bombonera-para-bombones-ceramica-frutilla-rojo-_JM
A75: {=XLOOKUP(B75,Costos_Proveedores!$B$2:$B$2000,Costos_Proveedores!$A$2:$A$2000)} -> MULI | B75: MLC2872122784 | C75: SP201075 | D75: Salero Y Pimentero Para Mesa De Ceramica Calabaza Multicolor | E75: active | G75: 1 | H75: =IF(I75="Sí",F75,F75+G75) -> 1 | I75: No | J75: =VLOOKUP(B75,Costos_Proveedores!$B$2:$J$1000,9,FALSE()) -> 1512 | K75: =IFERROR(H75*J75,0) -> 1512 | P75: =IF(M75>=F75,M75-F75,0) -> 0 | Q75: =IF(N75+O75-G75>=0,N75+O75-G75,0) -> 0 | R75: =P75+Q75 -> 0 | S75: https://articulo.mercadolibre.cl/MLC-2872122784-salero-y-pimentero-para-mesa-de-ceramica-calabaza-multicolor-_JM
A76: {=XLOOKUP(B76,Costos_Proveedores!$B$2:$B$2000,Costos_Proveedores!$A$2:$A$2000)} -> MULI | B76: MLC2872120342 | C76: SP201074 | D76: Servilletero Ceramica Porta Servilletas De Calabaza 11 Cm Multicolor | E76: active | G76: 1 | H76: =IF(I76="Sí",F76,F76+G76) -> 1 | I76: No | J76: =VLOOKUP(B76,Costos_Proveedores!$B$2:$J$1000,9,FALSE()) -> 1512 | K76: =IFERROR(H76*J76,0) -> 1512 | P76: =IF(M76>=F76,M76-F76,0) -> 0 | Q76: =IF(N76+O76-G76>=0,N76+O76-G76,0) -> 0 | R76: =P76+Q76 -> 0 | S76: https://articulo.mercadolibre.cl/MLC-2872120342-servilletero-ceramica-porta-servilletas-de-calabaza-11-cm-multicolor-_JM
A77: {=XLOOKUP(B77,Costos_Proveedores!$B$2:$B$2000,Costos_Proveedores!$A$2:$A$2000)} -> MULI | B77: MLC2872031222 | C77: SP201067 | D77: Tetera De Cerámica 850 Ml Calabaza Calabaza | E77: active | G77: 1 | H77: =IF(I77="Sí",F77,F77+G77) -> 1 | I77: No | J77: =VLOOKUP(B77,Costos_Proveedores!$B$2:$J$1000,9,FALSE()) -> 2520 | K77: =IFERROR(H77*J77,0) -> 2520 | P77: =IF(M77>=F77,M77-F77,0) -> 0 | Q77: =IF(N77+O77-G77>=0,N77+O77-G77,0) -> 0 | R77: =P77+Q77 -> 0 | S77: https://articulo.mercadolibre.cl/MLC-2872031222-tetera-de-ceramica-850-ml-calabaza-calabaza-_JM
A78: {=XLOOKUP(B78,Costos_Proveedores!$B$2:$B$2000,Costos_Proveedores!$A$2:$A$2000)} -> MULI | B78: MLC1598213735 | C78: TH21563 | D78: Salero Y Pimentero Para Mesa De Ceramica Frutilla Rojo | E78: paused | G78: 0 | H78: =IF(I78="Sí",F78,F78+G78) -> 0 | I78: No | J78: =VLOOKUP(B78,Costos_Proveedores!$B$2:$J$1000,9,FALSE()) -> 1680 | K78: =IFERROR(H78*J78,0) -> 0 | P78: =IF(M78>=F78,M78-F78,0) -> 0 | Q78: =IF(N78+O78-G78>=0,N78+O78-G78,0) -> 0 | R78: =P78+Q78 -> 0 | S78: https://articulo.mercadolibre.cl/MLC-1598213735-salero-y-pimentero-para-mesa-de-ceramica-frutilla-rojo-_JM
A79: {=XLOOKUP(B79,Costos_Proveedores!$B$2:$B$2000,Costos_Proveedores!$A$2:$A$2000)} -> MULI | B79: MLC1598182719 | C79: SP201078 | D79: Bombonera Con Tapa Bombonera Para Bombones Ceramica Calabaza Multicolor | E79: paused | G79: 0 | H79: =IF(I79="Sí",F79,F79+G79) -> 0 | I79: No | J79: =VLOOKUP(B79,Costos_Proveedores!$B$2:$J$1000,9,FALSE()) -> 3780 | K79: =IFERROR(H79*J79,0) -> 0 | P79: =IF(M79>=F79,M79-F79,0) -> 0 | Q79: =IF(N79+O79-G79>=0,N79+O79-G79,0) -> 0 | R79: =P79+Q79 -> 0 | S79: https://articulo.mercadolibre.cl/MLC-1598182719-bombonera-con-tapa-bombonera-para-bombones-ceramica-calabaza-multicolor-_JM
A80: {=XLOOKUP(B80,Costos_Proveedores!$B$2:$B$2000,Costos_Proveedores!$A$2:$A$2000)} -> MULI | B80: MLC1598163137 | C80: TH21550 | D80: Servilletero Ceramica Porta Servilletas De Frutilla 20 Cm Rojo | E80: paused | G80: 0 | H80: =IF(I80="Sí",F80,F80+G80) -> 0 | I80: No | J80: =VLOOKUP(B80,Costos_Proveedores!$B$2:$J$1000,9,FALSE()) -> 1176 | K80: =IFERROR(H80*J80,0) -> 0 | P80: =IF(M80>=F80,M80-F80,0) -> 0 | Q80: =IF(N80+O80-G80>=0,N80+O80-G80,0) -> 0 | R80: =P80+Q80 -> 0 | S80: https://articulo.mercadolibre.cl/MLC-1598163137-servilletero-ceramica-porta-servilletas-de-frutilla-20-cm-rojo-_JM
A81: {=XLOOKUP(B81,Costos_Proveedores!$B$2:$B$2000,Costos_Proveedores!$A$2:$A$2000)} -> MULI | B81: MLC1598150129 | C81: TH21543 | D81: Fuente Para Comida De Ceramica Frutilla 21cm Rojo | E81: paused | G81: 0 | H81: =IF(I81="Sí",F81,F81+G81) -> 0 | I81: No | J81: =VLOOKUP(B81,Costos_Proveedores!$B$2:$J$1000,9,FALSE()) -> 1848 | K81: =IFERROR(H81*J81,0) -> 0 | P81: =IF(M81>=F81,M81-F81,0) -> 0 | Q81: =IF(N81+O81-G81>=0,N81+O81-G81,0) -> 0 | R81: =P81+Q81 -> 0 | S81: https://articulo.mercadolibre.cl/MLC-1598150129-fuente-para-comida-de-ceramica-frutilla-21cm-rojo-_JM
A82: {=XLOOKUP(B82,Costos_Proveedores!$B$2:$B$2000,Costos_Proveedores!$A$2:$A$2000)} -> ZEO SPORT | B82: MLC2884354532 | C82: 659525122935 | D82: Citrato De Magnesio + L Triptófano 90 Capsulas Zeo Sport | E82: paused | F82: 0 | G82: 136 | H82: =IF(I82="Sí",F82,F82+G82) -> 0 | I82: Sí | J82: =VLOOKUP(B82,Costos_Proveedores!$B$2:$J$1000,9,FALSE()) -> 3808 | K82: =IFERROR(H82*J82,0) -> 0 | L82: 84 | M82: 81 | N82: 0 | O82: 0 | P82: =IF(M82>=F82,M82-F82,0) -> 81 | Q82: =IF(N82+O82-G82>=0,N82+O82-G82,0) -> 0 | R82: =P82+Q82 -> 81 | S82: https://articulo.mercadolibre.cl/MLC-2884354532-citrato-de-magnesio-l-triptofano-90-capsulas-zeo-sport-_JM
A83: {=XLOOKUP(B83,Costos_Proveedores!$B$2:$B$2000,Costos_Proveedores!$A$2:$A$2000)} -> ZEO SPORT | B83: MLC2884237924 | C83: 781718786164 | D83: Suplemento Zeo Sport Premium Citrato De Magnesio De 50g X 90 Unidades | E83: paused | F83: 0 | G83: 0 | H83: =IF(I83="Sí",F83,F83+G83) -> 0 | I83: Sí | J83: =VLOOKUP(B83,Costos_Proveedores!$B$2:$J$1000,9,FALSE()) -> 3558 | K83: =IFERROR(H83*J83,0) -> 0 | L83: 110 | M83: 110 | N83: 0 | O83: 0 | P83: =IF(M83>=F83,M83-F83,0) -> 110 | Q83: =IF(N83+O83-G83>=0,N83+O83-G83,0) -> 0 | R83: =P83+Q83 -> 110 | S83: https://articulo.mercadolibre.cl/MLC-2884237924-suplemento-zeo-sport-premium-citrato-de-magnesio-de-50g-x-90-unidades-_JM
A84: {=XLOOKUP(B84,Costos_Proveedores!$B$2:$B$2000,Costos_Proveedores!$A$2:$A$2000)} -> ZEO SPORT | B84: MLC2884186274 | C84: 745853432478 | D84: Citrato De Magnesio Zeo Sport 1 Kilo En Polvo Línea Premium | E84: paused | F84: 0 | G84: 41 | H84: =IF(I84="Sí",F84,F84+G84) -> 0 | I84: Sí | J84: =VLOOKUP(B84,Costos_Proveedores!$B$2:$J$1000,9,FALSE()) -> 16660 | K84: =IFERROR(H84*J84,0) -> 0 | L84: 73 | M84: 73 | N84: 0 | O84: 0 | P84: =IF(M84>=F84,M84-F84,0) -> 73 | Q84: =IF(N84+O84-G84>=0,N84+O84-G84,0) -> 0 | R84: =P84+Q84 -> 73 | S84: https://articulo.mercadolibre.cl/MLC-2884186274-citrato-de-magnesio-zeo-sport-1-kilo-en-polvo-linea-premium-_JM
A85: {=XLOOKUP(B85,Costos_Proveedores!$B$2:$B$2000,Costos_Proveedores!$A$2:$A$2000)} -> ZEO SPORT | B85: MLC2884173342 | C85: 659525123055 | D85: Bisglicinato De Magnesio Zeo Sport 1000mg 90 Cápsulas Veganas Sin Sabor Sin Sabor (90 Capsulas) | E85: paused | F85: 0 | G85: 5 | H85: =IF(I85="Sí",F85,F85+G85) -> 0 | I85: Sí | J85: =VLOOKUP(B85,Costos_Proveedores!$B$2:$J$1000,9,FALSE()) -> 4760 | K85: =IFERROR(H85*J85,0) -> 0 | L85: 526 | M85: 526 | N85: 0 | O85: 0 | P85: =IF(M85>=F85,M85-F85,0) -> 526 | Q85: =IF(N85+O85-G85>=0,N85+O85-G85,0) -> 0 | R85: =P85+Q85 -> 526 | S85: https://articulo.mercadolibre.cl/MLC-2884173342-bisglicinato-de-magnesio-zeo-sport-1000mg-90-capsulas-veganas-sin-sabor-sin-sabor-90-capsulas-_JM
A86: {=XLOOKUP(B86,Costos_Proveedores!$B$2:$B$2000,Costos_Proveedores!$A$2:$A$2000)} -> MULI | B86: MLC2884550352 | C86: TH21549 | D86: Mantequillera Con Tapa Mantequillera De Ceramica Frutilla Rojo | E86: paused | G86: 0 | H86: =IF(I86="Sí",F86,F86+G86) -> 0 | I86: No | J86: =VLOOKUP(B86,Costos_Proveedores!$B$2:$J$1000,9,FALSE()) -> 2520 | K86: =IFERROR(H86*J86,0) -> 0 | P86: =IF(M86>=F86,M86-F86,0) -> 0 | Q86: =IF(N86+O86-G86>=0,N86+O86-G86,0) -> 0 | R86: =P86+Q86 -> 0 | S86: https://articulo.mercadolibre.cl/MLC-2884550352-mantequillera-con-tapa-mantequillera-de-ceramica-frutilla-rojo-_JM
A87: {=XLOOKUP(B87,Costos_Proveedores!$B$2:$B$2000,Costos_Proveedores!$A$2:$A$2000)} -> CASO Y CIA | B87: MLC2886979324 | C87: SOBRES 710763 | D87: Super Zings Serie 3 Pack 10 Sobres 1 Figura Por Sobre | E87: paused | F87: 0 | G87: 0 | H87: =IF(I87="Sí",F87,F87+G87) -> 0 | I87: No | J87: =VLOOKUP(B87,Costos_Proveedores!$B$2:$J$1000,9,FALSE()) -> 5800 | K87: =IFERROR(H87*J87,0) -> 0 | P87: =IF(M87>=F87,M87-F87,0) -> 0 | Q87: =IF(N87+O87-G87>=0,N87+O87-G87,0) -> 0 | R87: =P87+Q87 -> 0 | S87: https://articulo.mercadolibre.cl/MLC-2886979324-super-zings-serie-3-pack-10-sobres-1-figura-por-sobre-_JM
A88: {=XLOOKUP(B88,Costos_Proveedores!$B$2:$B$2000,Costos_Proveedores!$A$2:$A$2000)} -> EXTREMO SUR | B88: MLC2886467526 | C88: Pack 3 Magnesio | D88: Citrato De Magnesio Cápsulas Extremo Sur 500mg Sin Sabor X270 Unidades | E88: paused | F88: 0 | G88: 5 | H88: =IF(I88="Sí",F88,F88+G88) -> 0 | I88: Sí | J88: =VLOOKUP(B88,Costos_Proveedores!$B$2:$J$1000,9,FALSE()) -> 10175 | K88: =IFERROR(H88*J88,0) -> 0 | P88: =IF(M88>=F88,M88-F88,0) -> 0 | Q88: =IF(N88+O88-G88>=0,N88+O88-G88,0) -> 0 | R88: =P88+Q88 -> 0 | S88: https://articulo.mercadolibre.cl/MLC-2886467526-citrato-de-magnesio-capsulas-extremo-sur-500mg-sin-sabor-x270-unidades-_JM
A89: {=XLOOKUP(B89,Costos_Proveedores!$B$2:$B$2000,Costos_Proveedores!$A$2:$A$2000)} -> EXTREMO SUR | B89: MLC2886227406 | C89: 7896108056567 | D89: Extremo Sur - Melena De Leon 500mg 60 Cap. 100% Natural | E89: paused | F89: 0 | G89: 0 | H89: =IF(I89="Sí",F89,F89+G89) -> 0 | I89: No | J89: =VLOOKUP(B89,Costos_Proveedores!$B$2:$J$1000,9,FALSE()) -> 4296 | K89: =IFERROR(H89*J89,0) -> 0 | P89: =IF(M89>=F89,M89-F89,0) -> 0 | Q89: =IF(N89+O89-G89>=0,N89+O89-G89,0) -> 0 | R89: =P89+Q89 -> 0 | S89: https://articulo.mercadolibre.cl/MLC-2886227406-extremo-sur-melena-de-leon-500mg-60-cap-100-natural-_JM
A90: {=XLOOKUP(B90,Costos_Proveedores!$B$2:$B$2000,Costos_Proveedores!$A$2:$A$2000)} -> EXTREMO SUR | B90: MLC2886162644 | C90: 7804651160235 | D90: Vitamina C 90 Cap De 500mg 100% Natural Extremo Sur | E90: paused | F90: 0 | G90: 84 | H90: =IF(I90="Sí",F90,F90+G90) -> 0 | I90: Sí | J90: =VLOOKUP(B90,Costos_Proveedores!$B$2:$J$1000,9,FALSE()) -> 2939 | K90: =IFERROR(H90*J90,0) -> 0 | P90: =IF(M90>=F90,M90-F90,0) -> 0 | Q90: =IF(N90+O90-G90>=0,N90+O90-G90,0) -> 0 | R90: =P90+Q90 -> 0 | S90: https://articulo.mercadolibre.cl/MLC-2886162644-vitamina-c-90-cap-de-500mg-100-natural-extremo-sur-_JM
A91: {=XLOOKUP(B91,Costos_Proveedores!$B$2:$B$2000,Costos_Proveedores!$A$2:$A$2000)} -> STRIVE | B91: MLC1608039965 | C91: Strive Magnesio | D91: Strive Magnesio + L Triptófano 60 Cápsulas Nutricional Sin Sabor | E91: active | F91: 201 | G91: 2 | H91: =IF(I91="Sí",F91,F91+G91) -> 201 | I91: Sí | J91: =VLOOKUP(B91,Costos_Proveedores!$B$2:$J$1000,9,FALSE()) -> 14168 | K91: =IFERROR(H91*J91,0) -> 2847768 | L91: 115 | M91: 124 | N91: 0 | O91: 0 | P91: =IF(M91>=F91,M91-F91,0) -> 0 | Q91: =IF(N91+O91-G91>=0,N91+O91-G91,0) -> 0 | R91: =P91+Q91 -> 0 | S91: https://articulo.mercadolibre.cl/MLC-1608039965-strive-magnesio-l-triptofano-60-capsulas-nutricional-sin-sabor-_JM
A92: {=XLOOKUP(B92,Costos_Proveedores!$B$2:$B$2000,Costos_Proveedores!$A$2:$A$2000)} -> CASO Y CIA | B92: MLC2888665676 | C92: 710763 | D92: Super Zings Serie 3 - Caja Sellada 25 Personajes | E92: paused | F92: 0 | G92: 0 | H92: =IF(I92="Sí",F92,F92+G92) -> 0 | I92: No | J92: =VLOOKUP(B92,Costos_Proveedores!$B$2:$J$1000,9,FALSE()) -> 14500 | K92: =IFERROR(H92*J92,0) -> 0 | P92: =IF(M92>=F92,M92-F92,0) -> 0 | Q92: =IF(N92+O92-G92>=0,N92+O92-G92,0) -> 0 | R92: =P92+Q92 -> 0 | S92: https://articulo.mercadolibre.cl/MLC-2888665676-super-zings-serie-3-caja-sellada-25-personajes-_JM
A93: {=XLOOKUP(B93,Costos_Proveedores!$B$2:$B$2000,Costos_Proveedores!$A$2:$A$2000)} -> STRIVE | B93: MLC2888575494 | C93: Screatina | D93: Creatina Monohidratada Micronizada - 300gr, Strive Sin Sabor Sin Sabor | E93: active | F93: 222 | G93: 6 | H93: =IF(I93="Sí",F93,F93+G93) -> 222 | I93: Sí | J93: =VLOOKUP(B93,Costos_Proveedores!$B$2:$J$1000,9,FALSE()) -> 16794 | K93: =IFERROR(H93*J93,0) -> 3728268 | L93: 121 | M93: 122 | N93: 0 | O93: 0 | P93: =IF(M93>=F93,M93-F93,0) -> 0 | Q93: =IF(N93+O93-G93>=0,N93+O93-G93,0) -> 0 | R93: =P93+Q93 -> 0 | S93: https://articulo.mercadolibre.cl/MLC-2888575494-creatina-monohidratada-micronizada-300gr-strive-sin-sabor-sin-sabor-_JM
A94: {=XLOOKUP(B94,Costos_Proveedores!$B$2:$B$2000,Costos_Proveedores!$A$2:$A$2000)} -> YOURGOAL | B94: MLC2888547512 | C94: 805164 | D94: Barras De Proteina Protein Bite Black & White Pack 4 Barrita | E94: active | F94: 353 | G94: 6 | H94: =IF(I94="Sí",F94,F94+G94) -> 353 | I94: Sí | J94: =VLOOKUP(B94,Costos_Proveedores!$B$2:$J$1000,9,FALSE()) -> 5780 | K94: =IFERROR(H94*J94,0) -> 2040340 | L94: 406 | M94: 352 | N94: 0 | O94: 0 | P94: =IF(M94>=F94,M94-F94,0) -> 0 | Q94: =IF(N94+O94-G94>=0,N94+O94-G94,0) -> 0 | R94: =P94+Q94 -> 0 | S94: https://articulo.mercadolibre.cl/MLC-2888547512-barras-de-proteina-protein-bite-black-white-pack-4-barrita-_JM
A95: {=XLOOKUP(B95,Costos_Proveedores!$B$2:$B$2000,Costos_Proveedores!$A$2:$A$2000)} -> YOURGOAL | B95: MLC1609044811 | C95: 805165 | D95: Barras De Proteinas Yourgoal Protein Bite 4u Caramel Peanuts Caramel Peanuts Salty | E95: paused | F95: 0 | G95: 0 | H95: =IF(I95="Sí",F95,F95+G95) -> 0 | I95: Sí | J95: =VLOOKUP(B95,Costos_Proveedores!$B$2:$J$1000,9,FALSE()) -> 5780 | K95: =IFERROR(H95*J95,0) -> 0 | L95: 320 | M95: 451 | N95: 0 | O95: 0 | P95: =IF(M95>=F95,M95-F95,0) -> 451 | Q95: =IF(N95+O95-G95>=0,N95+O95-G95,0) -> 0 | R95: =P95+Q95 -> 451 | S95: https://articulo.mercadolibre.cl/MLC-1609044811-barras-de-proteinas-yourgoal-protein-bite-4u-caramel-peanuts-caramel-peanuts-salty-_JM
A96: {=XLOOKUP(B96,Costos_Proveedores!$B$2:$B$2000,Costos_Proveedores!$A$2:$A$2000)} -> MULI | B96: MLC2890055674 | C96: WF33204 | D96: Pileta Fuente Cascada Agua Religiosa Niño Jesus San Jose Gris | E96: paused | F96: 0 | G96: 0 | H96: =IF(I96="Sí",F96,F96+G96) -> 0 | I96: No | J96: =VLOOKUP(B96,Costos_Proveedores!$B$2:$J$1000,9,FALSE()) -> 15000 | K96: =IFERROR(H96*J96,0) -> 0 | P96: =IF(M96>=F96,M96-F96,0) -> 0 | Q96: =IF(N96+O96-G96>=0,N96+O96-G96,0) -> 0 | R96: =P96+Q96 -> 0 | S96: https://articulo.mercadolibre.cl/MLC-2890055674-pileta-fuente-cascada-agua-religiosa-nino-jesus-san-jose-gris-_JM
A97: {=XLOOKUP(B97,Costos_Proveedores!$B$2:$B$2000,Costos_Proveedores!$A$2:$A$2000)} -> MULI | B97: MLC2892446834 | C97: 786428 | D97: Set27 5x5cm Abecedario Letras Gomaeva Bebe Alfombra Infantil Multicolor Abecedario | E97: active | F97: 4 | G97: 2 | H97: =IF(I97="Sí",F97,F97+G97) -> 6 | I97: No | J97: =VLOOKUP(B97,Costos_Proveedores!$B$2:$J$1000,9,FALSE()) -> $ 500 | K97: =IFERROR(H97*J97,0) -> 3000 | L97: 2 | M97: 2 | N97: 0 | O97: 0 | P97: =IF(M97>=F97,M97-F97,0) -> 0 | Q97: =IF(N97+O97-G97>=0,N97+O97-G97,0) -> 0 | R97: =P97+Q97 -> 0 | S97: https://articulo.mercadolibre.cl/MLC-2892446834-set27-5x5cm-abecedario-letras-gomaeva-bebe-alfombra-infantil-multicolor-abecedario-_JM
A98: {=XLOOKUP(B98,Costos_Proveedores!$B$2:$B$2000,Costos_Proveedores!$A$2:$A$2000)} -> MULI | B98: MLC2892393542 | C98: 786431 | D98: Set 29 9x9 Piezas Alfombra Goma Eva Cuadros Bebe Niños Multicolor Números | E98: paused | F98: 0 | G98: 7 | H98: =IF(I98="Sí",F98,F98+G98) -> 7 | I98: No | J98: =VLOOKUP(B98,Costos_Proveedores!$B$2:$J$1000,9,FALSE()) -> 1344 | K98: =IFERROR(H98*J98,0) -> 9408 | P98: =IF(M98>=F98,M98-F98,0) -> 0 | Q98: =IF(N98+O98-G98>=0,N98+O98-G98,0) -> 0 | R98: =P98+Q98 -> 0 | S98: https://articulo.mercadolibre.cl/MLC-2892393542-set-29-9x9-piezas-alfombra-goma-eva-cuadros-bebe-ninos-multicolor-numeros-_JM
A99: {=XLOOKUP(B99,Costos_Proveedores!$B$2:$B$2000,Costos_Proveedores!$A$2:$A$2000)} -> MULI | B99: MLC2892355596 | C99: 786432 | D99: Set 10 9x9cm Alfombra Infantil Goma Eva Cuadros Bebes Niños Multicolor Números | E99: paused | F99: 0 | G99: 2 | H99: =IF(I99="Sí",F99,F99+G99) -> 2 | I99: No | J99: =VLOOKUP(B99,Costos_Proveedores!$B$2:$J$1000,9,FALSE()) -> $ 400 | K99: =IFERROR(H99*J99,0) -> 800 | P99: =IF(M99>=F99,M99-F99,0) -> 0 | Q99: =IF(N99+O99-G99>=0,N99+O99-G99,0) -> 0 | R99: =P99+Q99 -> 0 | S99: https://articulo.mercadolibre.cl/MLC-2892355596-set-10-9x9cm-alfombra-infantil-goma-eva-cuadros-bebes-ninos-multicolor-numeros-_JM
A100: {=XLOOKUP(B100,Costos_Proveedores!$B$2:$B$2000,Costos_Proveedores!$A$2:$A$2000)} -> MULI | B100: MLC2892225070 | C100: 786430 | D100: Set 60 5x5 Alfombra Infantil Goma Eva Cuadros Bebes Numeros Multicolor Números | E100: paused | F100: 0 | G100: 5 | H100: =IF(I100="Sí",F100,F100+G100) -> 5 | I100: No | J100: =VLOOKUP(B100,Costos_Proveedores!$B$2:$J$1000,9,FALSE()) -> 1092 | K100: =IFERROR(H100*J100,0) -> 5460 | L100: 3 | M100: 3 | N100: 0 | O100: 0 | P100: =IF(M100>=F100,M100-F100,0) -> 3 | Q100: =IF(N100+O100-G100>=0,N100+O100-G100,0) -> 0 | R100: =P100+Q100 -> 3 | S100: https://articulo.mercadolibre.cl/MLC-2892225070-set-60-5x5-alfombra-infantil-goma-eva-cuadros-bebes-numeros-multicolor-numeros-_JM
...

Sheet Valorización
B2: Stock Declarado | C2: =SUM(Global!K2:K1011) -> 36108019
A4: STOCK NO DECLARADO
A5: STRIVE | B5: =260-52 -> 208 | C5: 14113 | D5: =B5*C5*1.19 -> 3493249.8
A6: STRIVE | B6: =260-52 -> 208 | C6: 15290 | D6: =B6*C6*1.19 -> 3784580.8
A7: STRIVE | B7: =260-52 -> 208 | C7: 15290 | D7: =B7*C7*1.19 -> 3784580.8
A8: SOMOS LOKAL | D8: 657554
A9: ZEO SPORT | D9: 2105967
A10: STRIVE | B10: 260 | D10: 5081338
B12: ACTIVOS | C12: VALORIZACION | D12: =SUM(D5:D10)+C2 -> 55015289
C13: CASH ON HAND | D13: 8303411
C14: CASH ON HAND (P) | D14: 6496096
B16: PASIVOS | C16: INFORMALES | D16: 41523355
C17: FORMALES | D17: 14389040
B19: NETO | D19: =D12+D13+D14-D16-D17 -> 13902401
B21: MENSUALIZADO | D21: =D19/9 -> 1544711.3
E22: M | F22: A | G22: Mayo | H22: Junio | I22: Julio | J22: Ag | K22: Sep | L22: Oct | M22: Nov
E23: 1 | F23: 2 | G23: 3 | H23: 4 | I23: 5 | J23: 6 | K23: 7 | L23: 8 | M23: 9 | N23: 12
E24: 300000 | F24: 2000000 | G24: 3500000 | H24: 4000000 | I24: 5000000 | J24: 5000000 | K24: 5000000 | L24: 5000000 | M24: 5000000
D25: Interes | E25: -2000000
D26: Sueldo | E26: =-170000-20000 -> -190000 | F26: =E26 -> -190000 | G26: =F26 -> -190000 | H26: =G26 -> -190000 | I26: =H26-150000 -> -340000 | J26: =I26 -> -340000 | K26: =J26-50000 -> -390000 | L26: =K26-50000 -> -440000 | M26: =L26-50000 -> -490000
D27: Muli | E27: -20000 | F27: -20000 | G27: -20000 | H27: -20000 | I27: -20000 | J27: -20000 | K27: -20000 | L27: -20000 | M27: -20000
D28: insumos | E28: -20000 | F28: -20000 | G28: -20000 | H28: -20000 | I28: -20000 | J28: -20000 | K28: -20000 | L28: -20000 | M28: -20000
D29: Chapa | F29: -150000
D30: Lavadora | G30: -420000
D31: Perruchas | L31: =-420000-690000 -> -1110000
D32: PPM | E32: -100000 | F32: -300000 | G32: -500000 | H32: -500000 | I32: -600000 | J32: -600000 | K32: -600000 | L32: -600000 | M32: -600000
D33: Neto | E33: =SUM(E24:E32) -> -2030000 | F33: =SUM(F24:F32) -> 1320000 | G33: =SUM(G24:G32) -> 2350000 | H33: =SUM(H24:H32) -> 3270000 | I33: =SUM(I24:I32) -> 4020000 | J33: =SUM(J24:J32) -> 4020000 | K33: =SUM(K24:K32) -> 3970000 | L33: =SUM(L24:L32) -> 2810000 | M33: =SUM(M24:M32) -> 3870000
D36: =SUM(E24:M24) -> 34800000 | E36: =SUM(E24:M32)+F36+G36+H36 -> 22414000 | F36: -550000 | G36: -11000 | H36: =-2500000/12*3 -> -625000
D37: =D36+E36 -> 57214000
D41: Casa Curauma | G41: -100000 | H41: -100000 | I41: -100000 | J41: -100000 | K41: -100000 | L41: -100000 | M41: -100000
D42: Casa stgo | J42: -150000 | K42: -150000 | L42: -150000 | M42: -150000

Sheet Costos_Proveedores
A1: Proveedor | B1: Número de publicación | C1: SKU | D1: Título | E1: Precio | F1: Comision % | G1: Comision $ | H1: Envio | I1: Ingreso | J1: Costo | K1: Utilidad | L1: Rentabilidad | M1: un x Caja Maestra
A2: ALMA | B2: MLC2906301858 | C2: 745853477929 | D2: Goldenmilk Tradicional 240 G Alma Golden Food - Leche Dorada | E2: $ 28,990 | F2: 0.1 | G2: $ 2,899 | H2: $ 3,100 | I2: $ 22,991 | J2: 12977 | K2: $ 10,014 | L2: 77.17% | M2: 1
A3: ALMA | B3: MLC2912910014 | C3: 745853477929 | D3: Goldenmilk Tradicional 240 G Alma Golden Food - Leche Dorada | E3: $ 19,738 | F3: 0.15 | G3: $ 2,961 | H3: $ - | I3: $ 16,777 | J3: 12977 | K3: $ 3,800 | L3: 29.28% | M3: 1
A4: ALMA | B4: MLC3009302444 | C4: Alma Matcha | D4: Goldenmilk Matcha 240 Gr - Leche Dorada Alma Foods | G4: $ - | I4: $ - | J4: 12977 | K4: $ (12,977) | L4: -100.00% | M4: 1
A5: ALMA | B5: MLC3009771438 | C5: Alma Cacao | D5: Goldenmilk Cacao 240 Gr - Leche Dorada Alma Foods | G5: $ - | I5: $ - | J5: 12977 | K5: $ (12,977) | L5: -100.00% | M5: 1
A6: ALMA | B6: MLC1726540139 | C6: Alma Matcha | D6: Goldenmilk Matcha 240 Gr - Leche Dorada Alma Foods | J6: 12977 | M6: 1
A7: BLENDS N TEA | B7: MLC2906248372 | C7: gdm100 | D7: Golden Milk 100 Gr Blends & Tea | E7: $ 11,990 | F7: 0.1 | G7: $ 2,199 | H7: $ - | I7: $ 9,791 | J7: 8033 | K7: $ 1,758 | L7: 21.88% | M7: 1
A8: BLENDS N TEA | B8: MLC2906348734 | C8: HD100 | D8: Te Hibisco Detox Vitalidad 100 Gr Blends & Tea | E8: $ 11,990 | F8: 0.15 | G8: $ 1,799 | H8: $ - | I8: $ 10,192 | J8: 8033 | K8: $ 2,159 | L8: 26.87% | M8: 1
A9: BLENDS N TEA | B9: MLC2938085790 | C9: gdm200 | D9: Golden Milk 200 gr Blends N Tea | E9: $ 19,980 | F9: 0.15 | G9: $ 2,997 | H9: $ - | I9: $ 16,983 | J9: 12054 | K9: $ 4,929 | L9: 40.90% | M9: 1
A10: BLENDS N TEA | B10: MLC2950215486 | C10: HD150 | D10: Te Hibisco Detox Vitalidad 150 Gr Blends & Tea | G10: $ - | I10: $ - | J10: 10043 | K10: $ (10,043) | L10: -100.00% | M10: 1
A11: BLENDS N TEA | B11: MLC3114523712 | C11: GDM150RG | D11: Golden Milk 150g Recarga Blends And Tea Curcuma | G11: $ - | I11: $ - | J11: 8033 | K11: $ (8,033) | L11: -100.00% | M11: 1
A12: BLENDS N TEA | B12: MLC3114447200 | C12: afm50 | D12: Infusión Armonía Fase Menstrual 50g Blends And Tea | G12: $ - | I12: $ - | J12: 6024 | K12: $ (6,024) | L12: -100.00% | M12: 1
A13: BLENDS N TEA | B13: MLC3114485416 | C13: afm150 | D13: Infusión Armonía Fase Menstrual 150g Blends And Tea | G13: $ - | I13: $ - | J13: 10042 | K13: $ (10,042) | L13: -100.00% | M13: 1
A14: BLENDS N TEA | B14: MLC3114472312 | C14: afmrg | D14: Infusión Armonía Fase Menstrual 100g Recarga | G14: $ - | I14: $ - | J14: 6694 | K14: $ (6,694) | L14: -100.00% | M14: 1
A15: BLENDS N TEA | B15: MLC3114601822 | C15: A50 | D15: Infusión Azul Relajante 50g | G15: $ - | I15: $ - | J15: 5354 | K15: $ (5,354) | L15: -100.00% | M15: 1
A16: BLENDS N TEA | B16: MLC3114549828 | C16: A100 | D16: Infusión Azul Relajante 100g Blends And Tea | G16: $ - | I16: $ - | J16: 8033 | K16: $ (8,033) | L16: -100.00% | M16: 1
A17: BLENDS N TEA | B17: MLC3114588654 | C17: A150 | D17: Infusión Azul Relajante 150g Blends And Tea | G17: $ - | I17: $ - | J17: 10042 | K17: $ (10,042) | L17: -100.00% | M17: 1
A18: BLENDS N TEA | B18: MLC3114537112 | C18: A100RG | D18: Infusión Azul Relajante 100g Recarga Blends And Tea | G18: $ - | I18: $ - | J18: 6694 | K18: $ (6,694) | L18: -100.00% | M18: 1
A19: BLENDS N TEA | B19: MLC3114472506 | C19: hsp50 | D19: Hibisco Sueño Profundo 50g Blends And Tea | G19: $ - | I19: $ - | J19: 5354 | K19: $ (5,354) | L19: -100.00% | M19: 1
A20: BLENDS N TEA | B20: MLC3114563012 | C20: hsp100 | D20: Hibisco Sueño Profundo 100g Blends And Tea | G20: $ - | I20: $ - | J20: 8033 | K20: $ (8,033) | L20: -100.00% | M20: 1
A21: BLENDS N TEA | B21: MLC3114537172 | C21: hsp150 | D21: Hibisco Sueño Profundo 150g Blends And Tea | G21: $ - | I21: $ - | J21: 10042 | K21: $ (10,042) | L21: -100.00% | M21: 1
... A75: BLENDS N TEA | B75: MLC3134950270 | C75: HD150 | D75: Te Hibisco Detox Vitalidad 150 Gr Blends & Tea | G75: $ - | I75: $ - | J75: 10043 | K75: $ (10,043) | L75: -100.00% | M75: 1
A76: BLENDS N TEA | B76: MLC1715850997 | C76: OC150 | D76: Te Oolong Manzana Canela 150g Blends And Tea | J76: 8033 | M76: 1
A77: CASO Y CIA | B77: MLC1608022999 | C77: PACK 4 710768 | D77: Pack 4 Superbot Serie 3 - Superzings Figuras Coleccionables | E77: $ 13,721 | F77: 0.16 | G77: $ 2,195 | H77: $ - | I77: $ 11,526 | J77: 6941 | K77: $ 4,585 | L77: 66.05% | M77: 1
A78: CASO Y CIA | B78: MLC2888665676 | C78: 710763 | D78: Super Zings Serie 3 - Caja Sellada 25 Personajes | E78: $ 24,240 | F78: 0.16 | G78: $ 3,878 | H78: $ 3,100 | I78: $ 17,262 | J78: 14500 | K78: $ 2,762 | L78: 19.05% | M78: 16
A79: CASO Y CIA | B79: MLC2902258430 | C79: 710798 | D79: Superzings Serie 3 Pack (comic + Superbot + 2 Fig + Slider) | E79: $ 7,990 | F79: 0.16 | G79: $ 1,278 | H79: $ - | I79: $ 6,712 | J79: 4665 | K79: $ 2,047 | L79: 43.87% | M79: 1
A80: CASO Y CIA | B80: MLC1621478293 | C80: Pack10TwoPack | D80: Pack 10 Sobres Twopack (villano + Heroe) Superzings Serie 3 | E80: $ 19,980 | F80: 0.16 | G80: $ 3,197 | H80: $ - | I80: $ 16,783 | J80: 11542 | K80: $ 5,241 | L80: 45.41% | M80: 24
A81: CASO Y CIA | B81: MLC2886979324 | C81: SOBRES 710763 | D81: Super Zings Serie 3 Pack 10 Sobres | E81: $ 10,838 | F81: 0.16 | G81: $ 2,758 | H81: $ - | I81: $ 8,080 | J81: 5800 | K81: $ 2,280 | L81: 39.31% | M81: 40
A82: CASO Y CIA | B82: MLC1607984995 | C82: 710766 | D82: 9+1 Superzings Dorado Coleccionables Superzings Serie 3 | E82: $ 15,980 | F82: 0.16 | G82: $ 2,557 | H82: $ - | I82: $ 13,423 | J82: 12094 | K82: $ 1,329 | L82: 10.99% | M82: 1
A83: CASO Y CIA | B83: MLC1607889075 | C83: 710765 | D83: Super Zings Superslider Blister 5 Figuras Serie 3 | E83: $ 11,989 | F83: 0.16 | G83: $ 1,918 | H83: $ - | I83: $ 10,071 | J83: 8793 | K83: $ 1,278 | L83: 14.53% | M83: 1
A84: CASO Y CIA | B84: MLC1607933771 | C84: SOBRES 710763 | D84: Pack 10 Sobres Superzings Figuras Coleccionables Serie 3 | E84: $ 10,525 | F84: 0.16 | G84: $ 2,684 | H84: $ - | I84: $ 7,841 | J84: 5800 | K84: $ 2,041 | L84: 35.19% | M84: 40
A85: CASO Y CIA | B85: MLC2887003786 | C85: 710765 | D85: 5 Figuras + Nave + Rampla Superzings Serie 3 Coleccionables | E85: $ 11,989 | F85: 0.16 | G85: $ 1,918 | H85: $ - | I85: $ 10,071 | J85: 8793 | K85: $ 1,278 | L85: 14.53% | M85: 1
A86: CASO Y CIA | B86: MLC1609718647 | C86: SOBRES 5 710763 | D86: Pack 5 Sobres Superzings Figuras Coleccionables Serie 3 | E86: $ 9,320 | F86: 0.16 | G86: $ 1,491 | H86: $ - | I86: $ 7,829 | J86: 3522 | K86: $ 4,307 | L86: 122.31% | M86: 1
A87: CASO Y CIA | B87: MLC2889808586 | C87: 710768 | D87: Superzings Caja 8 Superbots Figuras Coleccionables Serie 3 | E87: $ 33,311 | F87: 0.16 | G87: $ 5,330 | H87: $ 3,150 | I87: $ 24,831 | J87: 19278 | K87: $ 5,553 | L87: 28.81% | M87: 1
A88: CASO Y CIA | B88: MLC1646935669 | C88: Pack10TwoPack | D88: Pack 10 Sobres Twopack (villano + Heroe) Superzings Serie 3 | E88: $ 19,980 | F88: 0.16 | G88: $ 4,197 | H88: $ - | I88: $ 15,783 | J88: 11542 | K88: $ 4,241 | L88: 36.75% | M88: 1
A89: CASO Y CIA | B89: MLC2978633074 | C89: 710763 | D89: Super Zings Caja 25 Figuras Coleccionables Serie 3 | G89: $ - | I89: $ - | J89: 14500 | K89: $ (14,500) | L89: -100.00% | M89: 16
A90: CASO Y CIA | B90: MLC1703814075 | C90: 710837 Caja Completa Megajet | D90: Caja 8 Megajets + 8 Figuras Superzing Serie 4 | J90: 14698 | M90: 6
A91: CASO Y CIA | B91: MLC1703735977 | C91: 710837 Caja Completa Megajet | D91: Superzings Series 4 Display 8 Megajet + Figura | J91: 14698 | M91: 6
A92: CASO Y CIA | B92: MLC3174055132 | C92: 710837 Pack 4 Megajets | D92: Pack 4 Megajets + 4 Figuras Superzing Serie 4 | J92: 7349 | M92: 12
A93: CASO Y CIA | B93: MLC3173887108 | C93: 710843 Pack 5 Superjets | D93: Pack 5 Blaster Jets + 5 Figuras Superzing Serie 4 | J93: 9178 | M93: 38
A94: CASO Y CIA | B94: MLC3174055702 | C94: 710844 BLISTER BLASTER | D94: Pack 2 Blaster Jets + 4 Superzings Serie 4 | J94: 6745 | M94: 6
A95: CASO Y CIA | B95: MLC3174061226 | C95: 710842 Blister 10 figuras | D95: 9+1 Superzings Dorado Coleccionables Superzings Serie 4 | J95: 9206 | M95: 6
A96: CASO Y CIA | B96: MLC3173944846 | C96: 710841 Starterpack Comic | D96: Superzings Serie 4 Pack (comic + Megajet + 2 Fig + Bolsa) | J96: 4905 | M96: 12
A97: CASO Y CIA | B97: MLC3173918828 | C97: 710841 Starterpack Comic | D97: Super Zings Serie 4 Pack Inicial ( Comic + Pack Zings) | J97: 4905 | M97: 12
A98: CASO Y CIA | B98: MLC3174074694 | C98: 710838 Pack 10 Twopack Serie 4 | D98: Pack 10 Sobres Twopack (2 Figuras) Superzings Serie 4 | J98: 12215 | M98: 24
A99: CASO Y CIA | B99: MLC3173906610 | C99: 710840 Caja Sellada Serie 4 | D99: Caja Sellada 25 Sobres (1 Fig Por Sobre) Superzing Serie 4 | J99: 15343 | M99: 16
A100: CASO Y CIA | B100: MLC3174074946 | C100: 710840 Caja Sellada Serie 4 | D100: Figuritas Superzings One Serie 4 | J100: 15343 | M100: 16
A101: CASO Y CIA | B101: MLC3173945900 | C101: 710840 Pack 10 Sobres One pack serie 4 | D101: Pack 10 Sobres (1 Fig Por Sobre) Superzings Serie 4 | J101: 6137 | M101: 40
A102: CASO Y CIA | B102: MLC1710517921 | C102: 710844 BLISTER BLASTER | D102: Pack 2 Blaster Jets + 4 Superzings Serie 4 | J102: 6745 | M102: 6
A103: CEMAX | B103: MLC1669277943 | C103: 1173 | D103: Thomas Th-80n Cocedor De Huevos Color Negra | G103: $ - | I103: $ - | J103: 11893 | K103: $ (11,893) | L103: -100.00% | M103: 6
A104: CEMAX | B104: MLC1669075769 | C104: 1173 | D104: Thomas Th-80n Cocedor De Huevos Color Negra | G104: $ - | I104: $ - | J104: 11893 | K104: $ (11,893) | L104: -100.00% | M104: 6
A105: CEMAX | B105: MLC1668998351 | C105: 1120 | D105: Hervidor Thomas Th-4340 1,7 Litros Color Blanco | G105: $ - | I105: $ - | J105: 11893 | K105: $ (11,893) | L105: -100.00% | M105: 6
A106: CEMAX | B106: MLC1669011133 | C106: 1120 | D106: Hervidor Thomas Th-4340 1,7 Litros Color Blanco | G106: $ - | I106: $ - | J106: 11893 | K106: $ (11,893) | L106: -100.00% | M106: 6
A107: CEMAX | B107: MLC1669115003 | C107: 1408 | D107: Plancha De Vapor Th-7003 Color Blanco | G107: $ - | I107: $ - | J107: 10494 | K107: $ (10,494) | L107: -100.00% | M107: 10
A108: CEMAX | B108: MLC1669253391 | C108: 1408 | D108: Plancha De Vapor Th-7003 Color Blanco | G108: $ - | I108: $ - | J108: 10494 | K108: $ (10,494) | L108: -100.00% | M108: 10
A109: CEMAX | B109: MLC1669104065 | C109: 1234 | D109: Secador De Pelo Siegen Sg-3031 Color Púrpura | G109: $ - | I109: $ - | J109: 11893 | K109: $ (11,893) | L109: -100.00% | M109: 6
A110: CEMAX | B110: MLC1669000313 | C110: 1234 | D110: Secador De Pelo Siegen Sg-3031 Color Púrpura | G110: $ - | I110: $ - | J110: 11893 | K110: $ (11,893) | L110: -100.00% | M110: 6
A111: CEMAX | B111: MLC1669255479 | C111: 1283 | D111: Ondulador Siegen Sg-2411 Cilindro 25mm Color Negro | G111: $ - | I111: $ - | J111: 11194 | K111: $ (11,194) | L111: -100.00% | M111: 6
A112: CEMAX | B112: MLC1668961729 | C112: 1283 | D112: Ondulador Siegen Sg-2411 Cilindro 25mm Color Negro | G112: $ - | I112: $ - | J112: 11194 | K112: $ (11,194) | L112: -100.00% | M112: 6
A113: CEMAX | B113: MLC1668974445 | C113: 1432 | D113: Extractor De Jugo Th-2652i Color Gris | G113: $ - | I113: $ - | J113: 48994 | K113: $ (48,994) | L113: -100.00% | M113: 2
A114: CEMAX | B114: MLC1669130145 | C114: 1432 | D114: Extractor De Jugo Th-2652i Color Gris | G114: $ - | I114: $ - | J114: 48994 | K114: $ (48,994) | L114: -100.00% | M114: 2
... A130: CEMAX | B130: MLC1678034873 | C130: 1291 | D130: Trimmer Siegen Sg-8011 2en 1 Color Negro | G130: $ - | I130: $ - | J130: 6992 | K130: $ (6,992) | L130: -100.00% | M130: 12
A131: CEMAX | B131: MLC1710775847 | C131: 1134 | D131: Hervidor Thomas Th-6070vi 1,8 Litros Color Negro | J131: 27994 | M131: 4
A132: CEMAX | B132: MLC1710684845 | C132: 1134 | D132: Hervidor Thomas Th-6070vi 1,8 Litros Color Negro | J132: 27994 | M132: 4
A133: CEMAX | B133: MLC1710762837 | C133: 1267 | D133: Alisador Siegen Sg-4653 Placas Con Titanio | J133: 48993 | M133: 6
A134: CEMAX | B134: MLC1710658915 | C134: 1267 | D134: Alisador Siegen Sg-4653 Placas Con Titanio | J134: 48993 | M134: 6
A135: CEMAX | B135: MLC1710620417 | C135: 1221 | D135: Secador De Pelo Siegen Sg-3012 Negro | J135: 9793 | M135: 6
A136: CEMAX | B136: MLC1710697999 | C136: 1221 | D136: Secador De Pelo Siegen Sg-3012 Negro | J136: 9793 | M136: 6
A137: CEMAX | B137: MLC1710646589 | C137: 1340 | D137: Calienta Cama Siegen Sg-5121d5 2 Plazas (150 X 140 Cms) Colo | J137: 29393 | M137: 6
A138: CEMAX | B138: MLC1710685409 | C138: 1340 | D138: Calienta Cama Siegen Sg-5121d5 2 Plazas (150 X 140 Cms) Color Blanco | J138: 29393 | M138: 6
A139: CEMAX | B139: MLC1710711573 | C139: 1383 | D139: Multimixer Thomas Th-8706 | J139: 13993 | M139: 6
A140: CEMAX | B140: MLC1710685563 | C140: 1383 | D140: Multimixer Thomas Th-8706 | J140: 13993 | M140: 6
A141: CEMAX | B141: MLC1710673607 | C141: 1094 | D141: Aspiradora Thomas Th-1220af Aquafilter | J141: 104993 | M141: 1
A142: CEMAX | B142: MLC1710660395 | C142: 1094 | D142: Aspiradora Thomas Th-1220af Aquafilter | J142: 104993 | M142: 1
... A181: CEMAX | B181: MLC1716155885 | C181: 1108 | D181: Horno De Mesa Eléctrico Thomas 25litros Cocina Th-25n01 | J181: 38493 | M181: 1
A182: ESPACIO B | B182: MLC1611486875 | C182: COMJFM30095 | D182: Shampoo Controlgx Control Gx Just For Men Tinte Shampoo Y Shampoo Matizador De Coco En Tubo Depresible De 118ml Por 1 Unidad | E182: $ 14,044 | F182: 0.11 | G182: $ 2,545 | H182: $ - | I182: $ 11,499 | J182: 10615 | K182: $ 884 | L182: 8.33% | M182: 12
A183: ESPACIO B | B183: MLC1611370149 | C183: MUSCRF35631 | D183: Mustela Crema Facial Hydra Bebé Piel Normal 40ml | E183: $ 5,070 | F183: 0.17 | G183: $ 862 | H183: $ - | I183: $ 4,208 | J183: 3114 | K183: $ 1,094 | L183: 35.12% | M183: 6
A184: ESPACIO B | B184: MLC1611512641 | C184: KATIAB49236 | D184: Alisado Brasilero Para Todo Tipo De Cabello | E184: $ 11,025 | F184: 0.16 | G184: $ 1,764 | H184: $ - | I184: $ 9,261 | J184: 8574 | K184: $ 687 | L184: 8.01% | M184: 6
A185: ESPACIO B | B185: MLC1611318043 | C185: MUSGEL35617 | D185: Mustela Gel De Baño 500 Ml Botella | E185: $ 8,772 | F185: 0.18 | G185: $ 1,579 | H185: $ - | I185: $ 7,193 | J185: 5994 | K185: $ 1,199 | L185: 20.00% | M185: 6
A186: ESPACIO B | B186: MLC1617050221 | C186: MUSCRC35624 | D186: Mustela Hydra Bebé Leche Hidratante Corporal 300ml | E186: $ 9,298 | F186: 0.18 | G186: $ 1,674 | H186: $ - | I186: $ 7,624 | J186: 6355 | K186: $ 1,270 | L186: 19.98% | M186: 3
A187: ESPACIO B | B187: MLC1611564729 | C187: MUSCRF35631 | D187: Mustela Crema Facial Hydra Bebé Piel Normal 40ml | E187: $ 4,503 | F187: 0.17 | G187: $ 766 | H187: $ - | I187: $ 3,737 | J187: 3114 | K187: $ 623 | L187: 20.01% | M187: 6
A188: ESPACIO B | B188: MLC1616986129 | C188: MUSCRC35624 | D188: Mustela Hydra Bebé Leche Hidratante Corporal 300ml | E188: $ 9,298 | F188: 0.18 | G188: $ 1,674 | H188: $ - | I188: $ 7,624 | J188: 6355 | K188: $ 1,270 | L188: 19.98% | M188: 3
A189: ESPACIO B | B189: MLC1611344217 | C189: KATIAB49236 | D189: Alisado Brasilero Para Todo Tipo De Cabello | E189: $ 11,025 | F189: 0.16 | G189: $ 1,764 | H189: $ - | I189: $ 9,261 | J189: 8574 | K189: $ 687 | L189: 8.01% | M189: 6
A190: ESPACIO B | B190: MLC1611382963 | C190: MUSGEL35617 | D190: Mustela Gel De Baño 500 Ml Botella | E190: $ 8,772 | F190: 0.18 | G190: $ 1,579 | H190: $ - | I190: $ 7,193 | J190: 5994 | K190: $ 1,199 | L190: 20.00% | M190: 6
A191: ESPACIO B | B191: MLC1611551879 | C191: COMJFM30095 | D191: Shampoo Controlgx Control Gx Just For Men Tinte Shampoo Y Sh | E191: $ 15,436 | F191: 0.11 | G191: $ 2,698 | H191: $ - | I191: $ 12,738 | J191: 10615 | K191: $ 2,123 | L191: 20.00% | M191: 12
A192: ESPACIO B | B192: MLC1617062667 | C192: RESPIR00818 | D192: Breathe Right Tiras Nasales Anti Ronquido Piel Normal 10u | E192: $ 5,981 | F192: 0.2 | G192: $ 1,196 | H192: $ - | I192: $ 4,785 | J192: 3951 | K192: $ 834 | L192: 21.11% | M192: 12
A193: ESPACIO B | B193: MLC1611357713 | C193: ALPLO214218 | D193: Alpecin Anti Calvicie Loción Cafeína Líquida 200 Ml | E193: $ 10,990 | F193: 0.16 | G193: $ 2,758 | H193: $ - | I193: $ 8,232 | J193: 7014 | K193: $ 1,218 | L193: 17.36% | M193: 6
... A204: ESPACIO B | B204: MLC1623083375 | C204: KATIOI21624 | D204: Kativa Argan Oil Serum Reparador Brillo Cabello Seco X 60ml | E204: $ 4,790 | F204: 0.16 | G204: $ 766 | H204: $ - | I204: $ 4,024 | J204: 3834 | K204: $ 189 | L204: 4.94% | M204: 1
A205: ESPACIO B | B205: MLC1622916875 | C205: 3504105036126 | D205: Mustela Shampoo Suave 200 Ml | E205: $ 5,513 | F205: 0.16 | G205: $ 882 | H205: $ - | I205: $ 4,631 | J205: 3750 | K205: $ 881 | L205: 23.50% | M205: 3
A206: ESPACIO B | B206: MLC1623133639 | C206: 3504105036126 | D206: Mustela Shampoo Suave 200 Ml | E206: $ 5,356 | F206: 0.16 | G206: $ 857 | H206: $ - | I206: $ 4,499 | J206: 3750 | K206: $ 749 | L206: 19.98% | M206: 3
A207: ESPACIO B | B207: MLC2908930024 | C207: KATIOI24885 | D207: Protector Térmico 12 Beneficios Brillo Reparación Kativa Cvl | E207: $ 6,876 | F207: 0.16 | G207: $ 1,100 | H207: $ - | I207: $ 5,776 | J207: 4493 | K207: $ 1,282 | L207: 28.54% | M207: 1
A208: ESPACIO B | B208: MLC1623095205 | C208: KATIOI24885 | D208: Protector Térmico 12 Beneficios Brillo Reparación Kativa Cvl | E208: $ 6,876 | F208: 0.16 | G208: $ 1,100 | H208: $ - | I208: $ 5,776 | J208: 4493 | K208: $ 1,282 | L208: 28.54% | M208: 1
A209: ESPACIO B | B209: MLC1623107989 | C209: KATITP63044 | D209: Kit Tratamiento Reconstrucción Capilar Kativa Total Plex | E209: $ 11,826 | F209: 0.16 | G209: $ 1,892 | H209: $ - | I209: $ 9,934 | J209: 7723 | K209: $ 2,211 | L209: 28.63% | M209: 6
A210: ESPACIO B | B210: MLC1623120909 | C210: KATITP63044 | D210: Kit Tratamiento Reconstrucción Capilar Kativa Total Plex | E210: $ 11,826 | F210: 0.16 | G210: $ 1,892 | H210: $ - | I210: $ 9,934 | J210: 7723 | K210: $ 2,211 | L210: 28.63% | M210: 6
A211: ESPACIO B | B211: MLC2908972996 | C211: KATIAS50099 | D211: Alisado Kativa Sin Plancha Xtreme Care 150ml Reconstruye | E211: $ 12,618 | F211: 0.16 | G211: $ 2,019 | H211: $ - | I211: $ 10,599 | J211: 8274 | K211: $ 2,325 | L211: 28.10% | M211: 1
A212: ESPACIO B | B212: MLC1623120933 | C212: KATIAS50099 | D212: Alisado Kativa Sin Plancha Xtreme Care 150ml Reconstruye | E212: $ 12,618 | F212: 0.16 | G212: $ 2,019 | H212: $ - | I212: $ 10,599 | J212: 8274 | K212: $ 2,325 | L212: 28.10% | M212: 1
A213: ESPACIO B | B213: MLC1623083477 | C213: COMARG40507 | D213: Dermo Vagisil Jabón Líquido Odor Block 354ml | E213: $ 8,490 | F213: 0.16 | G213: $ 1,358 | H213: $ - | I213: $ 7,132 | J213: 4799 | K213: $ 2,332 | L213: 48.60% | M213: 3
A214: ESPACIO B | B214: MLC1623120955 | C214: COMARG40507 | D214: Dermo Vagisil Jabón Líquido Odor Block 354ml | E214: $ 8,490 | F214: 0.16 | G214: $ 1,358 | H214: $ - | I214: $ 7,132 | J214: 4799 | K214: $ 2,332 | L214: 48.60% | M214: 3
A215: ESPACIO B | B215: MLC1623058243 | C215: 736658953275 | D215: Cepillo Para Cabello Wetbrush Shine Enhacer Desenredante Col | E215: $ 11,990 | F215: 0.13 | G215: $ 2,559 | H215: $ - | I215: $ 9,431 | J215: 8443 | K215: $ 988 | L215: 11.70% | M215: 4
A216: ESPACIO B | B216: MLC2908954280 | C216: 736658953275 | D216: Cepillo Para Cabello Wetbrush Shine Enhacer Desenredante Col | E216: $ 11,990 | F216: 0.13 | G216: $ 2,559 | H216: $ - | I216: $ 9,431 | J216: 8443 | K216: $ 988 | L216: 11.70% | M216: 4
...
